Workbook

Sheet Dashboard
B2: DPDPA Compliance Dashboard
B3: Kavach Financial Technologies Private Limited · assessed 2026-08-14 · all figures recalculate from the Control Matrix
B5: OVERALL MATURITY
B6: Weighted maturity score | C6: =G33 | I6: Weighted by domain, so a domain with many controls does not mechanically dominate one with few but weighty ones.
B7: Maturity band | C7: =IF(C6="","Not assessed",IF(C6>=0.8,"Optimised",IF(C6>=0.6,"Managed",IF(C6>=0.4,"Developing",IF(C6>=0.2,"Initial","Absent")))))
B8: Assessment coverage | C8: =IF(D33=0,"",E33/D33)
B9: Controls in scope / assessed | C9: =D33&" / "&E33
B10: Total gaps identified | C10: =F33
B11: Critical-severity gaps | C11: =COUNTIFS('Control Matrix'!$R$2:$R$91,1,'Control Matrix'!$E$2:$E$91,"Critical")
B14: MATURITY BY DOMAIN
B15: Domain | C15: Weight | D15: In scope | E15: Assessed | F15: Gaps | G15: Maturity | H15: Wtd num. | I15: Wtd den. | J15: Band
B16: APP — Applicability & Role Determination | C16: 1 | D16: =COUNTIFS('Control Matrix'!$B$2:$B$91,"APP",'Control Matrix'!$H$2:$H$91,"Yes") | E16: =COUNTIFS('Control Matrix'!$B$2:$B$91,"APP",'Control Matrix'!$N$2:$N$91,1) | F16: =COUNTIFS('Control Matrix'!$B$2:$B$91,"APP",'Control Matrix'!$R$2:$R$91,1) | G16: =IF(SUMIFS('Control Matrix'!$T$2:$T$91,'Control Matrix'!$B$2:$B$91,"APP")=0,"",SUMIFS('Control Matrix'!$S$2:$S$91,'Control Matrix'!$B$2:$B$91,"APP")/SUMIFS('Control Matrix'!$T$2:$T$91,'Control Matrix'!$B$2:$B$91,"APP")) | H16: =IF(G16="","",G16*C16) | I16: =IF(G16="","",C16) | J16: =IF(G16="","Not assessed",IF(G16>=0.8,"Optimised",IF(G16>=0.6,"Managed",IF(G16>=0.4,"Developing",IF(G16>=0.2,"Initial","Absent")))))
B17: GOV — Governance, Accountability & Records | C17: 1.2 | D17: =COUNTIFS('Control Matrix'!$B$2:$B$91,"GOV",'Control Matrix'!$H$2:$H$91,"Yes") | E17: =COUNTIFS('Control Matrix'!$B$2:$B$91,"GOV",'Control Matrix'!$N$2:$N$91,1) | F17: =COUNTIFS('Control Matrix'!$B$2:$B$91,"GOV",'Control Matrix'!$R$2:$R$91,1) | G17: =IF(SUMIFS('Control Matrix'!$T$2:$T$91,'Control Matrix'!$B$2:$B$91,"GOV")=0,"",SUMIFS('Control Matrix'!$S$2:$S$91,'Control Matrix'!$B$2:$B$91,"GOV")/SUMIFS('Control Matrix'!$T$2:$T$91,'Control Matrix'!$B$2:$B$91,"GOV")) | H17: =IF(G17="","",G17*C17) | I17: =IF(G17="","",C17) | J17: =IF(G17="","Not assessed",IF(G17>=0.8,"Optimised",IF(G17>=0.6,"Managed",IF(G17>=0.4,"Developing",IF(G17>=0.2,"Initial","Absent")))))
B18: PUR — Lawful Purpose, Minimisation & Accuracy | C18: 1 | D18: =COUNTIFS('Control Matrix'!$B$2:$B$91,"PUR",'Control Matrix'!$H$2:$H$91,"Yes") | E18: =COUNTIFS('Control Matrix'!$B$2:$B$91,"PUR",'Control Matrix'!$N$2:$N$91,1) | F18: =COUNTIFS('Control Matrix'!$B$2:$B$91,"PUR",'Control Matrix'!$R$2:$R$91,1) | G18: =IF(SUMIFS('Control Matrix'!$T$2:$T$91,'Control Matrix'!$B$2:$B$91,"PUR")=0,"",SUMIFS('Control Matrix'!$S$2:$S$91,'Control Matrix'!$B$2:$B$91,"PUR")/SUMIFS('Control Matrix'!$T$2:$T$91,'Control Matrix'!$B$2:$B$91,"PUR")) | H18: =IF(G18="","",G18*C18) | I18: =IF(G18="","",C18) | J18: =IF(G18="","Not assessed",IF(G18>=0.8,"Optimised",IF(G18>=0.6,"Managed",IF(G18>=0.4,"Developing",IF(G18>=0.2,"Initial","Absent")))))
B19: NOT — Notice | C19: 1.1 | D19: =COUNTIFS('Control Matrix'!$B$2:$B$91,"NOT",'Control Matrix'!$H$2:$H$91,"Yes") | E19: =COUNTIFS('Control Matrix'!$B$2:$B$91,"NOT",'Control Matrix'!$N$2:$N$91,1) | F19: =COUNTIFS('Control Matrix'!$B$2:$B$91,"NOT",'Control Matrix'!$R$2:$R$91,1) | G19: =IF(SUMIFS('Control Matrix'!$T$2:$T$91,'Control Matrix'!$B$2:$B$91,"NOT")=0,"",SUMIFS('Control Matrix'!$S$2:$S$91,'Control Matrix'!$B$2:$B$91,"NOT")/SUMIFS('Control Matrix'!$T$2:$T$91,'Control Matrix'!$B$2:$B$91,"NOT")) | H19: =IF(G19="","",G19*C19) | I19: =IF(G19="","",C19) | J19: =IF(G19="","Not assessed",IF(G19>=0.8,"Optimised",IF(G19>=0.6,"Managed",IF(G19>=0.4,"Developing",IF(G19>=0.2,"Initial","Absent")))))
B20: CON — Consent | C20: 1.3 | D20: =COUNTIFS('Control Matrix'!$B$2:$B$91,"CON",'Control Matrix'!$H$2:$H$91,"Yes") | E20: =COUNTIFS('Control Matrix'!$B$2:$B$91,"CON",'Control Matrix'!$N$2:$N$91,1) | F20: =COUNTIFS('Control Matrix'!$B$2:$B$91,"CON",'Control Matrix'!$R$2:$R$91,1) | G20: =IF(SUMIFS('Control Matrix'!$T$2:$T$91,'Control Matrix'!$B$2:$B$91,"CON")=0,"",SUMIFS('Control Matrix'!$S$2:$S$91,'Control Matrix'!$B$2:$B$91,"CON")/SUMIFS('Control Matrix'!$T$2:$T$91,'Control Matrix'!$B$2:$B$91,"CON")) | H20: =IF(G20="","",G20*C20) | I20: =IF(G20="","",C20) | J20: =IF(G20="","Not assessed",IF(G20>=0.8,"Optimised",IF(G20>=0.6,"Managed",IF(G20>=0.4,"Developing",IF(G20>=0.2,"Initial","Absent")))))
B21: CMG — Consent Manager | C21: 0.8 | D21: =COUNTIFS('Control Matrix'!$B$2:$B$91,"CMG",'Control Matrix'!$H$2:$H$91,"Yes") | E21: =COUNTIFS('Control Matrix'!$B$2:$B$91,"CMG",'Control Matrix'!$N$2:$N$91,1) | F21: =COUNTIFS('Control Matrix'!$B$2:$B$91,"CMG",'Control Matrix'!$R$2:$R$91,1) | G21: =IF(SUMIFS('Control Matrix'!$T$2:$T$91,'Control Matrix'!$B$2:$B$91,"CMG")=0,"",SUMIFS('Control Matrix'!$S$2:$S$91,'Control Matrix'!$B$2:$B$91,"CMG")/SUMIFS('Control Matrix'!$T$2:$T$91,'Control Matrix'!$B$2:$B$91,"CMG")) | H21: =IF(G21="","",G21*C21) | I21: =IF(G21="","",C21) | J21: =IF(G21="","Not assessed",IF(G21>=0.8,"Optimised",IF(G21>=0.6,"Managed",IF(G21>=0.4,"Developing",IF(G21>=0.2,"Initial","Absent")))))
B22: LGU — Legitimate Uses | C22: 0.9 | D22: =COUNTIFS('Control Matrix'!$B$2:$B$91,"LGU",'Control Matrix'!$H$2:$H$91,"Yes") | E22: =COUNTIFS('Control Matrix'!$B$2:$B$91,"LGU",'Control Matrix'!$N$2:$N$91,1) | F22: =COUNTIFS('Control Matrix'!$B$2:$B$91,"LGU",'Control Matrix'!$R$2:$R$91,1) | G22: =IF(SUMIFS('Control Matrix'!$T$2:$T$91,'Control Matrix'!$B$2:$B$91,"LGU")=0,"",SUMIFS('Control Matrix'!$S$2:$S$91,'Control Matrix'!$B$2:$B$91,"LGU")/SUMIFS('Control Matrix'!$T$2:$T$91,'Control Matrix'!$B$2:$B$91,"LGU")) | H22: =IF(G22="","",G22*C22) | I22: =IF(G22="","",C22) | J22: =IF(G22="","Not assessed",IF(G22>=0.8,"Optimised",IF(G22>=0.6,"Managed",IF(G22>=0.4,"Developing",IF(G22>=0.2,"Initial","Absent")))))
B23: RET — Retention & Erasure | C23: 1.1 | D23: =COUNTIFS('Control Matrix'!$B$2:$B$91,"RET",'Control Matrix'!$H$2:$H$91,"Yes") | E23: =COUNTIFS('Control Matrix'!$B$2:$B$91,"RET",'Control Matrix'!$N$2:$N$91,1) | F23: =COUNTIFS('Control Matrix'!$B$2:$B$91,"RET",'Control Matrix'!$R$2:$R$91,1) | G23: =IF(SUMIFS('Control Matrix'!$T$2:$T$91,'Control Matrix'!$B$2:$B$91,"RET")=0,"",SUMIFS('Control Matrix'!$S$2:$S$91,'Control Matrix'!$B$2:$B$91,"RET")/SUMIFS('Control Matrix'!$T$2:$T$91,'Control Matrix'!$B$2:$B$91,"RET")) | H23: =IF(G23="","",G23*C23) | I23: =IF(G23="","",C23) | J23: =IF(G23="","Not assessed",IF(G23>=0.8,"Optimised",IF(G23>=0.6,"Managed",IF(G23>=0.4,"Developing",IF(G23>=0.2,"Initial","Absent")))))
B24: RGT — Data Principal Rights | C24: 1.1 | D24: =COUNTIFS('Control Matrix'!$B$2:$B$91,"RGT",'Control Matrix'!$H$2:$H$91,"Yes") | E24: =COUNTIFS('Control Matrix'!$B$2:$B$91,"RGT",'Control Matrix'!$N$2:$N$91,1) | F24: =COUNTIFS('Control Matrix'!$B$2:$B$91,"RGT",'Control Matrix'!$R$2:$R$91,1) | G24: =IF(SUMIFS('Control Matrix'!$T$2:$T$91,'Control Matrix'!$B$2:$B$91,"RGT")=0,"",SUMIFS('Control Matrix'!$S$2:$S$91,'Control Matrix'!$B$2:$B$91,"RGT")/SUMIFS('Control Matrix'!$T$2:$T$91,'Control Matrix'!$B$2:$B$91,"RGT")) | H24: =IF(G24="","",G24*C24) | I24: =IF(G24="","",C24) | J24: =IF(G24="","Not assessed",IF(G24>=0.8,"Optimised",IF(G24>=0.6,"Managed",IF(G24>=0.4,"Developing",IF(G24>=0.2,"Initial","Absent")))))
B25: GRV — Grievance Redressal | C25: 1 | D25: =COUNTIFS('Control Matrix'!$B$2:$B$91,"GRV",'Control Matrix'!$H$2:$H$91,"Yes") | E25: =COUNTIFS('Control Matrix'!$B$2:$B$91,"GRV",'Control Matrix'!$N$2:$N$91,1) | F25: =COUNTIFS('Control Matrix'!$B$2:$B$91,"GRV",'Control Matrix'!$R$2:$R$91,1) | G25: =IF(SUMIFS('Control Matrix'!$T$2:$T$91,'Control Matrix'!$B$2:$B$91,"GRV")=0,"",SUMIFS('Control Matrix'!$S$2:$S$91,'Control Matrix'!$B$2:$B$91,"GRV")/SUMIFS('Control Matrix'!$T$2:$T$91,'Control Matrix'!$B$2:$B$91,"GRV")) | H25: =IF(G25="","",G25*C25) | I25: =IF(G25="","",C25) | J25: =IF(G25="","Not assessed",IF(G25>=0.8,"Optimised",IF(G25>=0.6,"Managed",IF(G25>=0.4,"Developing",IF(G25>=0.2,"Initial","Absent")))))
B26: SEC — Security Safeguards | C26: 1.4 | D26: =COUNTIFS('Control Matrix'!$B$2:$B$91,"SEC",'Control Matrix'!$H$2:$H$91,"Yes") | E26: =COUNTIFS('Control Matrix'!$B$2:$B$91,"SEC",'Control Matrix'!$N$2:$N$91,1) | F26: =COUNTIFS('Control Matrix'!$B$2:$B$91,"SEC",'Control Matrix'!$R$2:$R$91,1) | G26: =IF(SUMIFS('Control Matrix'!$T$2:$T$91,'Control Matrix'!$B$2:$B$91,"SEC")=0,"",SUMIFS('Control Matrix'!$S$2:$S$91,'Control Matrix'!$B$2:$B$91,"SEC")/SUMIFS('Control Matrix'!$T$2:$T$91,'Control Matrix'!$B$2:$B$91,"SEC")) | H26: =IF(G26="","",G26*C26) | I26: =IF(G26="","",C26) | J26: =IF(G26="","Not assessed",IF(G26>=0.8,"Optimised",IF(G26>=0.6,"Managed",IF(G26>=0.4,"Developing",IF(G26>=0.2,"Initial","Absent")))))
B27: BRC — Personal Data Breach Notification | C27: 1.3 | D27: =COUNTIFS('Control Matrix'!$B$2:$B$91,"BRC",'Control Matrix'!$H$2:$H$91,"Yes") | E27: =COUNTIFS('Control Matrix'!$B$2:$B$91,"BRC",'Control Matrix'!$N$2:$N$91,1) | F27: =COUNTIFS('Control Matrix'!$B$2:$B$91,"BRC",'Control Matrix'!$R$2:$R$91,1) | G27: =IF(SUMIFS('Control Matrix'!$T$2:$T$91,'Control Matrix'!$B$2:$B$91,"BRC")=0,"",SUMIFS('Control Matrix'!$S$2:$S$91,'Control Matrix'!$B$2:$B$91,"BRC")/SUMIFS('Control Matrix'!$T$2:$T$91,'Control Matrix'!$B$2:$B$91,"BRC")) | H27: =IF(G27="","",G27*C27) | I27: =IF(G27="","",C27) | J27: =IF(G27="","Not assessed",IF(G27>=0.8,"Optimised",IF(G27>=0.6,"Managed",IF(G27>=0.4,"Developing",IF(G27>=0.2,"Initial","Absent")))))
B28: CHD — Children & Persons with Disability | C28: 1.2 | D28: =COUNTIFS('Control Matrix'!$B$2:$B$91,"CHD",'Control Matrix'!$H$2:$H$91,"Yes") | E28: =COUNTIFS('Control Matrix'!$B$2:$B$91,"CHD",'Control Matrix'!$N$2:$N$91,1) | F28: =COUNTIFS('Control Matrix'!$B$2:$B$91,"CHD",'Control Matrix'!$R$2:$R$91,1) | G28: =IF(SUMIFS('Control Matrix'!$T$2:$T$91,'Control Matrix'!$B$2:$B$91,"CHD")=0,"",SUMIFS('Control Matrix'!$S$2:$S$91,'Control Matrix'!$B$2:$B$91,"CHD")/SUMIFS('Control Matrix'!$T$2:$T$91,'Control Matrix'!$B$2:$B$91,"CHD")) | H28: =IF(G28="","",G28*C28) | I28: =IF(G28="","",C28) | J28: =IF(G28="","Not assessed",IF(G28>=0.8,"Optimised",IF(G28>=0.6,"Managed",IF(G28>=0.4,"Developing",IF(G28>=0.2,"Initial","Absent")))))
B29: PRO — Processors & Vendor Contracts | C29: 1.1 | D29: =COUNTIFS('Control Matrix'!$B$2:$B$91,"PRO",'Control Matrix'!$H$2:$H$91,"Yes") | E29: =COUNTIFS('Control Matrix'!$B$2:$B$91,"PRO",'Control Matrix'!$N$2:$N$91,1) | F29: =COUNTIFS('Control Matrix'!$B$2:$B$91,"PRO",'Control Matrix'!$R$2:$R$91,1) | G29: =IF(SUMIFS('Control Matrix'!$T$2:$T$91,'Control Matrix'!$B$2:$B$91,"PRO")=0,"",SUMIFS('Control Matrix'!$S$2:$S$91,'Control Matrix'!$B$2:$B$91,"PRO")/SUMIFS('Control Matrix'!$T$2:$T$91,'Control Matrix'!$B$2:$B$91,"PRO")) | H29: =IF(G29="","",G29*C29) | I29: =IF(G29="","",C29) | J29: =IF(G29="","Not assessed",IF(G29>=0.8,"Optimised",IF(G29>=0.6,"Managed",IF(G29>=0.4,"Developing",IF(G29>=0.2,"Initial","Absent")))))
B30: XBD — Cross-Border Transfers | C30: 0.9 | D30: =COUNTIFS('Control Matrix'!$B$2:$B$91,"XBD",'Control Matrix'!$H$2:$H$91,"Yes") | E30: =COUNTIFS('Control Matrix'!$B$2:$B$91,"XBD",'Control Matrix'!$N$2:$N$91,1) | F30: =COUNTIFS('Control Matrix'!$B$2:$B$91,"XBD",'Control Matrix'!$R$2:$R$91,1) | G30: =IF(SUMIFS('Control Matrix'!$T$2:$T$91,'Control Matrix'!$B$2:$B$91,"XBD")=0,"",SUMIFS('Control Matrix'!$S$2:$S$91,'Control Matrix'!$B$2:$B$91,"XBD")/SUMIFS('Control Matrix'!$T$2:$T$91,'Control Matrix'!$B$2:$B$91,"XBD")) | H30: =IF(G30="","",G30*C30) | I30: =IF(G30="","",C30) | J30: =IF(G30="","Not assessed",IF(G30>=0.8,"Optimised",IF(G30>=0.6,"Managed",IF(G30>=0.4,"Developing",IF(G30>=0.2,"Initial","Absent")))))
B31: SDF — Significant Data Fiduciary Obligations | C31: 1.2 | D31: =COUNTIFS('Control Matrix'!$B$2:$B$91,"SDF",'Control Matrix'!$H$2:$H$91,"Yes") | E31: =COUNTIFS('Control Matrix'!$B$2:$B$91,"SDF",'Control Matrix'!$N$2:$N$91,1) | F31: =COUNTIFS('Control Matrix'!$B$2:$B$91,"SDF",'Control Matrix'!$R$2:$R$91,1) | G31: =IF(SUMIFS('Control Matrix'!$T$2:$T$91,'Control Matrix'!$B$2:$B$91,"SDF")=0,"",SUMIFS('Control Matrix'!$S$2:$S$91,'Control Matrix'!$B$2:$B$91,"SDF")/SUMIFS('Control Matrix'!$T$2:$T$91,'Control Matrix'!$B$2:$B$91,"SDF")) | H31: =IF(G31="","",G31*C31) | I31: =IF(G31="","",C31) | J31: =IF(G31="","Not assessed",IF(G31>=0.8,"Optimised",IF(G31>=0.6,"Managed",IF(G31>=0.4,"Developing",IF(G31>=0.2,"Initial","Absent")))))
B32: BRD — Enforcement Readiness & Board Engagement | C32: 0.7 | D32: =COUNTIFS('Control Matrix'!$B$2:$B$91,"BRD",'Control Matrix'!$H$2:$H$91,"Yes") | E32: =COUNTIFS('Control Matrix'!$B$2:$B$91,"BRD",'Control Matrix'!$N$2:$N$91,1) | F32: =COUNTIFS('Control Matrix'!$B$2:$B$91,"BRD",'Control Matrix'!$R$2:$R$91,1) | G32: =IF(SUMIFS('Control Matrix'!$T$2:$T$91,'Control Matrix'!$B$2:$B$91,"BRD")=0,"",SUMIFS('Control Matrix'!$S$2:$S$91,'Control Matrix'!$B$2:$B$91,"BRD")/SUMIFS('Control Matrix'!$T$2:$T$91,'Control Matrix'!$B$2:$B$91,"BRD")) | H32: =IF(G32="","",G32*C32) | I32: =IF(G32="","",C32) | J32: =IF(G32="","Not assessed",IF(G32>=0.8,"Optimised",IF(G32>=0.6,"Managed",IF(G32>=0.4,"Developing",IF(G32>=0.2,"Initial","Absent")))))
B33: TOTAL / WEIGHTED | D33: =SUM(D16:D32) | E33: =SUM(E16:E32) | F33: =SUM(F16:F32) | G33: =IF(SUM(I16:I32)=0,"",SUM(H16:H32)/SUM(I16:I32))
B36: STATUS SUMMARY
B37: Compliant | C37: =COUNTIFS('Control Matrix'!$O$2:$O$91,"Compliant")
B38: Substantially compliant | C38: =COUNTIFS('Control Matrix'!$O$2:$O$91,"Substantially compliant")
B39: Partially compliant | C39: =COUNTIFS('Control Matrix'!$O$2:$O$91,"Partially compliant")
B40: Non-compliant | C40: =COUNTIFS('Control Matrix'!$O$2:$O$91,"Non-compliant")
B41: Not assessed | C41: =COUNTIFS('Control Matrix'!$O$2:$O$91,"Not assessed")
B42: Not applicable | C42: =COUNTIFS('Control Matrix'!$O$2:$O$91,"Not applicable")
B43: Out of scope | C43: =COUNTIFS('Control Matrix'!$O$2:$O$91,"Out of scope")
B45: GAPS BY SEVERITY
B46: Critical | C46: =COUNTIFS('Control Matrix'!$R$2:$R$91,1,'Control Matrix'!$E$2:$E$91,"Critical")
B47: High | C47: =COUNTIFS('Control Matrix'!$R$2:$R$91,1,'Control Matrix'!$E$2:$E$91,"High")
B48: Medium | C48: =COUNTIFS('Control Matrix'!$R$2:$R$91,1,'Control Matrix'!$E$2:$E$91,"Medium")
B49: Low | C49: =COUNTIFS('Control Matrix'!$R$2:$R$91,1,'Control Matrix'!$E$2:$E$91,"Low")
B51: PENALTY EXPOSURE — SCHEDULE ENTRIES ENGAGED
B52: Schedule entry | C52: Provision | D52: Max (INR cr) | E52: Gaps | F52: Engaged | G52: Exposure (INR cr) | J52: Breach
B53: Entry 1 | C53: s.8(5) | D53: 250 | E53: =COUNTIFS('Control Matrix'!$R$2:$R$91,1,'Control Matrix'!$AD$2:$AD$91,1) | F53: =IF(E53>0,"Yes","No") | G53: =IF(AND(E53>0,ISNUMBER(D53)),D53,0) | J53: Breach of the obligation to take reasonable security safeguards to prevent personal data breach
B54: Entry 2 | C54: s.8(6) | D54: 200 | E54: =COUNTIFS('Control Matrix'!$R$2:$R$91,1,'Control Matrix'!$AD$2:$AD$91,2) | F54: =IF(E54>0,"Yes","No") | G54: =IF(AND(E54>0,ISNUMBER(D54)),D54,0) | J54: Breach of the obligation to give the Board or affected Data Principal notice of a personal data breach
B55: Entry 3 | C55: s.9 | D55: 200 | E55: =COUNTIFS('Control Matrix'!$R$2:$R$91,1,'Control Matrix'!$AD$2:$AD$91,3) | F55: =IF(E55>0,"Yes","No") | G55: =IF(AND(E55>0,ISNUMBER(D55)),D55,0) | J55: Breach of additional obligations in relation to children
B56: Entry 4 | C56: s.10 | D56: 150 | E56: =COUNTIFS('Control Matrix'!$R$2:$R$91,1,'Control Matrix'!$AD$2:$AD$91,4) | F56: =IF(E56>0,"Yes","No") | G56: =IF(AND(E56>0,ISNUMBER(D56)),D56,0) | J56: Breach of additional obligations of a Significant Data Fiduciary
B57: Entry 5 | C57: s.15 | D57: 0.001 | E57: =COUNTIFS('Control Matrix'!$R$2:$R$91,1,'Control Matrix'!$AD$2:$AD$91,5) | F57: =IF(E57>0,"Yes","No") | G57: =IF(AND(E57>0,ISNUMBER(D57)),D57,0) | J57: Breach of the duties of a Data Principal
B58: Entry 6 | C58: s.32 | D58: n/a | E58: =COUNTIFS('Control Matrix'!$R$2:$R$91,1,'Control Matrix'!$AD$2:$AD$91,6) | F58: =IF(E58>0,"Yes","No") | G58: =IF(AND(E58>0,ISNUMBER(D58)),D58,0) | J58: Breach of any term of a voluntary undertaking accepted by the Board
B59: Entry 7 | C59: residuary | D59: 50 | E59: =COUNTIFS('Control Matrix'!$R$2:$R$91,1,'Control Matrix'!$AD$2:$AD$91,7) | F59: =IF(E59>0,"Yes","No") | G59: =IF(AND(E59>0,ISNUMBER(D59)),D59,0) | J59: Breach of any other provision of the Act or rules made thereunder (residuary)
B60: AGGREGATE CEILING | G60: =SUM(G53:G59)
B62: This is a ceiling under the Schedule, not an estimate of any penalty that would in fact be imposed. Section 33(2) requires the Board to have regard to the nature and gravity of the breach, its duration and repetitive nature, the type of personal data affected, mitigating action and its timeliness and effectiveness, and proportionality. Documented, prompt remediation is an express mitigating factor.

Sheet Company Profile
B2: Company Profile & Engagement Details
B3: Yellow cells are inputs. Applicability flags determine which controls are in scope.
B5: ENTITY
B6: Legal name | C6: Kavach Financial Technologies Private Limited
B7: Trading name | C7: KavachPay
B8: Sector | C8: Financial services — consumer lending, UPI payments and prepaid instruments
B9: Registered office | C9: Level 7, Prestige Zeta, Whitefield Main Road, Bengaluru 560066, Karnataka, India
B10: Headcount | C10: 1180
B11: Data Principals (approx.) | C11: 14200000
B12: Business description | C12: KavachPay operates a consumer financial services platform in India comprising a UPI payments application, an unsecured personal and consumer-durable lending business originated digitally and co-lent with two partner NBFCs, a prepaid payment instrument wallet, and 'Kavach Junior', a supervised prepaid card and savings product marketed to 13-17 year olds under a parent's account. Onboarding is fully digital and relies on third-party KYC and bureau services. The entity was notified as a Significant Data Fiduciary and participates in the account aggregator ecosystem as a Financial Information User, receiving financial information through a registered Consent Manager.
B14: ENGAGEMENT
B15: Assessment date | C15: 2026-08-14
B16: Auditor | C16: Nandita Krishnan, CIPP/E, CISA
B17: Firm | C17: Sentinel Assurance LLP, Chartered Accountants
B18: Engagement reference | C18: SA/DPDP/2026/0417
B19: Scope statement | C19: An assessment of the design and operating effectiveness of the entity's arrangements for compliance with the Digital Personal Data Protection Act, 2023 across the digital personal data processing activities of Kavach Financial Technologies Private Limited and its collections subsidiary, covering the systems and activities listed in the scope schedule. Fieldwork was performed between 27 July and 14 August 2026 and comprised document inspection, 19 process walkthroughs with control owners, inspection of system configuration, and substantive testing of consent, withdrawal, rights and erasure journeys on live and non-production environments.
B21: APPLICABILITY FLAGS
B22: Flag | C22: Value | D22: Meaning
B23: is_sdf | C23: Yes | D23: Notified by the Central Government as a Significant Data Fiduciary under s.10(1). Set True only on actual notification, not on self-assessment.
B24: processes_children_data | C24: Yes | D24: Processes personal data of individuals under 18, or of persons with a lawful guardian. Defaults True because age is rarely reliably excluded.
B25: processes_employee_data | C25: Yes | D25: Processes personal data of employees, workers or contractors.
B26: uses_consent_manager | C26: Yes | D26: Receives or manages consent through a registered Consent Manager under s.6(7).
B27: is_consent_manager | C27: No | D27: The entity itself acts as a Consent Manager and requires registration under s.6(8).
B28: has_pre_commencement_data | C28: Yes | D28: Holds personal data processed on the basis of consent given before commencement, engaging the retrospective notice duty under s.5(2).
B29: regulated_sector | C29: Yes | D29: Subject to sectoral regulation that may impose stricter localisation or transfer requirements preserved by s.16(2) — banking, payments, insurance, telecom, securities, health.
B30: claims_exemption | C30: No | D30: Claims any exemption under s.17, including the class-based route in s.17(3).
B31: startup_exempt_s8_3 | C31: No | D31: Exempt from s.8(3) as a notified class under s.17(3). Requires actual notification.
B32: startup_exempt_s8_7 | C32: No | D32: Exempt from s.8(7) as a notified class under s.17(3). Requires actual notification.
B33: startup_exempt_s11 | C33: No | D33: Exempt from s.11 as a notified class under s.17(3). Requires actual notification.
B35: Note: changing a flag here does not re-filter the Control Matrix. Update the profile in the toolkit and regenerate, so that scope changes are recorded in the assessment file rather than only in the workbook.

Sheet Instructions
B2: DPDPA Compliance Audit — Control Matrix Workbook
B3: Digital Personal Data Protection Act, 2023 · control library v1.0.0 · 90 controls across 17 domains
B6: HOW TO USE THIS WORKBOOK
B7: Live model | C7: This is a working model, not a static export. The Score column on the Control Matrix is the only scoring input. Risk, status, gap flags, domain maturity, the overall score and the penalty-exposure table are formulas and update as soon as a score changes.
B8: Cells to edit | C8: Yellow cells only. On the Control Matrix these are Score (M), Finding (U), Evidence ref (V), Owner (W) and Target date (X). On Company Profile they are the value column. Every other cell is either reference text from the control library or a formula — overwriting a formula will break the dashboard.
B9: Scoring scale | C9: The library defines anchored descriptors for 0, 2 and 4; 1 and 3 are intermediate positions. Score the position you can evidence, not the intent. 0 = Absent — no capability · 1 = Initial — ad hoc, undocumented · 2 = Developing — partial, inconsistent · 3 = Managed — substantially in place, minor gaps · 4 = Optimised — complete, evidenced, tested
B10: Not applicable | C10: Enter NA where a control genuinely cannot apply. NA removes the control from the denominator. Do not score an inapplicable control 0 — that understates maturity and manufactures a gap that cannot be remediated.
B11: Out of scope | C11: Controls shown as In scope = No were excluded automatically by the applicability flags on the Company Profile sheet, with the reason given in column I. Change a flag and regenerate from the toolkit to bring them into scope.
B12: Gap threshold | C12: A control scoring below 3 of 4 is reported as a gap. 3 is the 'substantially in place, minor gaps' anchor, so the register captures every control where the obligation could not be concluded met.
B13: Risk score | C13: Risk = severity rank × (4 − score), range 0 to 16. Severity ranks are critical 4, high 3, medium 2, low 1. Risk therefore reflects both the seriousness of the obligation and how far short the entity falls. Bands: 12+ Critical, 8-11 High, 4-7 Medium, 1-3 Low.
B15: CITATIONS — READ THIS
B16: Act references | C16: Column J cites the DPDP Act, 2023. These are stated with confidence.
B17: Rules references | C17: Column K shows '[Rules citation to be verified]' wherever the rule number was not available when the library was authored. This is deliberate: a wrong statutory citation in a signed report passes review and reaches the regulator, whereas a blank one does not. Populate controls/citations.yaml once and every output updates. The Citations sheet lists each outstanding slot.
B18: Commencement | C18: The commencement position of individual provisions was not confirmed. Findings are compliance gaps against the framework as a whole; do not characterise a gap as a contravention of a provision without first confirming that it is in force.
B20: PENALTY EXPOSURE
B21: What it shows | C21: The Dashboard aggregates the statutory maxima under the Schedule to the Act for those entries engaged by controls currently scored below the gap threshold.
B22: What it is not | C22: It is a ceiling, not a prediction. Section 33(2) requires the Board to have regard to gravity, duration, the data affected, proportionality and mitigating action. Any penalty actually imposed would be a fraction of the ceiling, and documented prompt remediation is an express mitigating factor.
B24: LEGEND
B25: Yellow fill | C25: Input cell — edit this
B26: White / grey | C26: Reference text or formula — do not overwrite

Sheet Control Matrix
A1: Control ID | B1: Domain | C1: Domain name | D1: Control title | E1: Severity | F1: Sev rank | G1: Weight | H1: In scope | I1: Scope reason | J1: Act reference | K1: Rules reference | L1: Rules status | M1: Score (0-4 / NA) | N1: Scored | O1: Status | P1: Risk | Q1: Risk band | R1: Gap | S1: Contribution | T1: Max contribution | U1: Finding | V1: Evidence ref | W1: Owner | X1: Target date | Y1: Obligation | Z1: Audit question | AA1: Test procedure | AB1: Evidence expected | AC1: Penalty exposure | AD1: Penalty entry | AE1: Required target state (level 4)
A2: APP-01 | B2: APP | C2: Applicability & Role Determination | D2: Territorial and material applicability assessed | E2: High | F2: =IF(E2="Critical",4,IF(E2="High",3,IF(E2="Medium",2,1))) | G2: 1.2 | H2: Yes | I2: in scope | J2: s.3(a), s.3(b), DPDP Act, 2023 | K2: — | L2: — | M2: 3 | N2: =IF(OR(H2="No",M2="",UPPER(M2)="NA"),0,1) | O2: =IF(H2="No","Out of scope",IF(UPPER(M2)="NA","Not applicable",IF(M2="","Not assessed",IF(M2>=4,"Compliant",IF(M2>=3,"Substantially compliant",IF(M2>=2,"Partially compliant","Non-compliant")))))) | P2: =IF(N2=0,"",F2*(4-M2)) | Q2: =IF(P2="","",IF(P2>=12,"Critical",IF(P2>=8,"High",IF(P2>=4,"Medium",IF(P2>=1,"Low","None"))))) | R2: =IF(AND(N2=1,M2<3),1,0) | S2: =IF(N2=0,"",M2*G2) | T2: =IF(N2=0,"",4*G2) | U2: A written applicability analysis dated 12 February 2026 concludes that the entity processes digital personal data within India as a Data Fiduciary and additionally offers goods and services to Data Principals in India from a Singapore-incorporated affiliate. The analysis is sound but has not been revisited since the Kavach Junior launch in April 2026. | V2: WP-001 | W2: Meera Raghunathan, Head of Legal & Compliance | Y2: The Act applies to processing of digital personal data within India, and to processing outside India where it is in connection with any activity related to offering goods or services to Data Principals within India. The entity must have determined, and be able to explain, why the Act applies to it and to which processing activities. | Z2: Has the entity documented a reasoned applicability assessment covering both India-based processing and any offshore processing connected with offering goods or services into India? Does it correctly treat personal data collected in non-digital form and subsequently digitised as in scope? | AA2: Inspect the applicability assessment; enquire of legal/privacy owner; corroborate against the entity's actual product footprint and entity structure. | AB2: Written applicability assessment or scoping memorandum, dated and owned · List of legal entities, branches and offshore affiliates that process personal data of individuals in India · Confirmation of treatment of digitised paper records | AC2: Up to INR 50 crore | AD2: 7 | AE2: A documented, dated and reviewed assessment covers all entities and processing activities, correctly addresses extraterritorial reach and digitised records, and is refreshed when the product or entity footprint changes.
A3: APP-02 | B3: APP | C3: Applicability & Role Determination | D3: Role determination — Data Fiduciary versus Data Processor | E3: Critical | F3: =IF(E3="Critical",4,IF(E3="High",3,IF(E3="Medium",2,1))) | G3: 1.3 | H3: Yes | I3: in scope | J3: s.2, DPDP Act, 2023 (definitions of "Data Fiduciary", "Data Processor" and "Data Principal"), read with s.8(1) | K3: — | L3: — | M3: 2 | N3: =IF(OR(H3="No",M3="",UPPER(M3)="NA"),0,1) | O3: =IF(H3="No","Out of scope",IF(UPPER(M3)="NA","Not applicable",IF(M3="","Not assessed",IF(M3>=4,"Compliant",IF(M3>=3,"Substantially compliant",IF(M3>=2,"Partially compliant","Non-compliant")))))) | P3: =IF(N3=0,"",F3*(4-M3)) | Q3: =IF(P3="","",IF(P3>=12,"Critical",IF(P3>=8,"High",IF(P3>=4,"Medium",IF(P3>=1,"Low","None"))))) | R3: =IF(AND(N3=1,M3<3),1,0) | S3: =IF(N3=0,"",M3*G3) | T3: =IF(N3=0,"",4*G3) | U3: Role determination has been performed for the co-lending arrangements and for the KYC vendors, but not for the marketing stack. CleverTap and the Meta Custom Audiences integration are treated as processors in the vendor register while the contractual terms and the practical control over onward use point to an independent fiduciary role for the advertising platforms. The mischaracterisation understates the notice and consent obligations attaching to those disclosures. | V3: WP-002 | W3: Meera Raghunathan, Head of Legal & Compliance | Y3: The entity must correctly determine, for each processing activity, whether it acts as a Data Fiduciary (alone or jointly), determining the purpose and means of processing, or as a Data Processor acting on another's behalf. | Z3: Is there an activity-level role mapping? Where the entity claims to be only a Data Processor, does the evidence support that it does not determine purpose or means — including for any analytics, product improvement, model training or marketing it performs on the same data? | AA3: Inspect role mapping; re-perform the determination for a sample of three activities, testing the claim against contracts and actual data use. | AB3: Activity-level register recording role assumed and the basis for it · Customer or client contracts supporting a processor characterisation · Evidence that no independent purposes are pursued on processor-held data | AC3: Up to INR 50 crore | AD3: 7 | AE3: Roles are determined per activity, documented with reasoning, consistent with contracts and observed data flows, and re-tested when new uses such as model training are introduced.
A4: APP-03 | B4: APP | C4: Applicability & Role Determination | D4: Exemptions claimed are valid and evidenced | E4: High | F4: =IF(E4="Critical",4,IF(E4="High",3,IF(E4="Medium",2,1))) | G4: 1 | H4: No | I4: requires claims_exemption | J4: s.17(1), s.17(2), s.17(3), s.17(4), DPDP Act, 2023 | K4: [Rules citation to be verified] | L4: VERIFY_AGAINST_NOTIFIED_RULES | N4: =IF(OR(H4="No",M4="",UPPER(M4)="NA"),0,1) | O4: =IF(H4="No","Out of scope",IF(UPPER(M4)="NA","Not applicable",IF(M4="","Not assessed",IF(M4>=4,"Compliant",IF(M4>=3,"Substantially compliant",IF(M4>=2,"Partially compliant","Non-compliant")))))) | P4: =IF(N4=0,"",F4*(4-M4)) | Q4: =IF(P4="","",IF(P4>=12,"Critical",IF(P4>=8,"High",IF(P4>=4,"Medium",IF(P4>=1,"Low","None"))))) | R4: =IF(AND(N4=1,M4<3),1,0) | S4: =IF(N4=0,"",M4*G4) | T4: =IF(N4=0,"",4*G4) | Y4: Exemptions under section 17 apply only in the circumstances specified. The startup and class-based exemption under section 17(3) operates only in favour of classes of Data Fiduciary actually notified by the Central Government, and covers only the specified provisions. | Z4: Does the entity claim any exemption? If it claims the section 17(3) route, can it show that it falls within a class actually notified, rather than relying on self-identification as a startup? Is the claim limited to the provisions the exemption actually reaches? | AA4: Inspect the exemption claim and supporting notification; test the scope claimed against the provisions the exemption covers. | AB4: Written exemption analysis identifying the specific limb relied upon · Evidence of falling within a notified class, where section 17(3) is relied upon · Confirmation that obligations outside the exemption's scope continue to be met | AC4: Up to INR 50 crore | AD4: 7 | AE4: Either no exemption is claimed, or the claim is narrowly scoped, evidenced against a notified class, and obligations outside its reach are demonstrably still met.
A5: APP-04 | B5: APP | C5: Applicability & Role Determination | D5: Significant Data Fiduciary exposure assessed | E5: Medium | F5: =IF(E5="Critical",4,IF(E5="High",3,IF(E5="Medium",2,1))) | G5: 0.9 | H5: No | I5: excluded by is_sdf | J5: s.10(1), DPDP Act, 2023 | K5: — | L5: — | N5: =IF(OR(H5="No",M5="",UPPER(M5)="NA"),0,1) | O5: =IF(H5="No","Out of scope",IF(UPPER(M5)="NA","Not applicable",IF(M5="","Not assessed",IF(M5>=4,"Compliant",IF(M5>=3,"Substantially compliant",IF(M5>=2,"Partially compliant","Non-compliant")))))) | P5: =IF(N5=0,"",F5*(4-M5)) | Q5: =IF(P5="","",IF(P5>=12,"Critical",IF(P5>=8,"High",IF(P5>=4,"Medium",IF(P5>=1,"Low","None"))))) | R5: =IF(AND(N5=1,M5<3),1,0) | S5: =IF(N5=0,"",M5*G5) | T5: =IF(N5=0,"",4*G5) | Y5: The Central Government may notify a Data Fiduciary or class of Data Fiduciaries as Significant, having regard to the volume and sensitivity of personal data processed, risk to the rights of Data Principals, potential effects on the sovereignty and integrity of India, risk to electoral democracy, security of the State and public order. | Z5: Has the entity assessed its likelihood of designation against the section 10(1) factors, and does it have a plan to stand up section 10(2) capability within a realistic period of being notified? | AA5: Inspect the self-assessment against each statutory factor; enquire as to readiness planning. | AB5: Self-assessment against each of the section 10(1) factors · Readiness plan for DPO appointment, DPIA, independent audit and algorithmic due diligence · Board or management minute acknowledging the exposure | AC5: — | AE5: A documented assessment against each factor exists, is periodically refreshed, and a costed readiness plan is approved so that designation would not require a standing start.
A6: APP-05 | B6: APP | C6: Applicability & Role Determination | D6: Commencement and phasing tracked against the compliance plan | E6: High | F6: =IF(E6="Critical",4,IF(E6="High",3,IF(E6="Medium",2,1))) | G6: 1.1 | H6: Yes | I6: in scope | J6: s.1(2), DPDP Act, 2023 | K6: [Rules citation to be verified] | L6: VERIFY_AGAINST_NOTIFIED_RULES | M6: 1 | N6: =IF(OR(H6="No",M6="",UPPER(M6)="NA"),0,1) | O6: =IF(H6="No","Out of scope",IF(UPPER(M6)="NA","Not applicable",IF(M6="","Not assessed",IF(M6>=4,"Compliant",IF(M6>=3,"Substantially compliant",IF(M6>=2,"Partially compliant","Non-compliant")))))) | P6: =IF(N6=0,"",F6*(4-M6)) | Q6: =IF(P6="","",IF(P6>=12,"Critical",IF(P6>=8,"High",IF(P6>=4,"Medium",IF(P6>=1,"Low","None"))))) | R6: =IF(AND(N6=1,M6<3),1,0) | S6: =IF(N6=0,"",M6*G6) | T6: =IF(N6=0,"",4*G6) | U6: The compliance plan carries a single milestone described as 'DPDP readiness' with no linkage to the commencement of individual provisions or to the phasing of the Rules. Management could not demonstrate a mechanism for tracking notifications, so a provision coming into force would not automatically trigger a change in the plan. | V6: WP-003 | W6: Meera Raghunathan, Head of Legal & Compliance | Y6: Provisions of the Act and the Rules come into force on such dates as are appointed, which may differ across provisions. The entity must know which obligations are presently enforceable and which are forthcoming. | Z6: Does the entity maintain a current view of which provisions are in force, with its remediation plan sequenced against those dates rather than against an assumption that everything is either live or not yet live? | AA6: Inspect the compliance calendar; corroborate the dates recorded against the commencement notification. | AB6: Compliance calendar mapping obligations to commencement dates · Remediation plan sequenced against those dates · Evidence of monitoring for further notifications | AC6: — | AE6: A maintained calendar tracks each tranche, remediation is sequenced against it, and a named owner monitors for further notifications and Board guidance.
A7: GOV-01 | B7: GOV | C7: Governance, Accountability & Records | D7: Accountability for compliance, including processor activity | E7: Critical | F7: =IF(E7="Critical",4,IF(E7="High",3,IF(E7="Medium",2,1))) | G7: 1.3 | H7: Yes | I7: in scope | J7: s.8(1), DPDP Act, 2023 | K7: — | L7: — | M7: 2 | N7: =IF(OR(H7="No",M7="",UPPER(M7)="NA"),0,1) | O7: =IF(H7="No","Out of scope",IF(UPPER(M7)="NA","Not applicable",IF(M7="","Not assessed",IF(M7>=4,"Compliant",IF(M7>=3,"Substantially compliant",IF(M7>=2,"Partially compliant","Non-compliant")))))) | P7: =IF(N7=0,"",F7*(4-M7)) | Q7: =IF(P7="","",IF(P7>=12,"Critical",IF(P7>=8,"High",IF(P7>=4,"Medium",IF(P7>=1,"Low","None"))))) | R7: =IF(AND(N7=1,M7<3),1,0) | S7: =IF(N7=0,"",M7*G7) | T7: =IF(N7=0,"",4*G7) | U7: Accountability is asserted in the Information Privacy Policy v2.1 and the Head of Legal & Compliance is named as owner. However the policy is silent on the entity's responsibility for processing carried out by processors on its behalf, and the collections subsidiary operates its own dialler and call recording estate without the parent's oversight of that processing. | V7: WP-010 | W7: Meera Raghunathan, Head of Legal & Compliance | Y7: A Data Fiduciary is responsible for complying with the Act in respect of any processing undertaken by it or on its behalf by a Data Processor, notwithstanding any agreement to the contrary or the Data Principal's failure to carry out their duties. | Z7: Is there a named, senior accountable owner for DPDPA compliance whose remit expressly extends to processing carried out by processors, with sufficient authority and resourcing to act? | AA7: Inspect the appointment and remit; enquire of the owner as to authority, budget and escalation path; corroborate with governance minutes. | AB7: Written appointment recording name, role and remit · Governance forum terms of reference and minutes evidencing oversight · Evidence of resourcing and of escalation to senior management or the board | AC7: Up to INR 50 crore | AD7: 7 | AE7: A senior owner is formally appointed with an express remit covering processors, reports periodically to a governance forum or the board, and can evidence decisions actually taken under that authority.
A8: GOV-02 | B8: GOV | C8: Governance, Accountability & Records | D8: Record of processing activities maintained | E8: Critical | F8: =IF(E8="Critical",4,IF(E8="High",3,IF(E8="Medium",2,1))) | G8: 1.3 | H8: Yes | I8: in scope | J8: s.6(10), s.8(1), DPDP Act, 2023 (evidential requirement) | K8: — | L8: — | M8: 2 | N8: =IF(OR(H8="No",M8="",UPPER(M8)="NA"),0,1) | O8: =IF(H8="No","Out of scope",IF(UPPER(M8)="NA","Not applicable",IF(M8="","Not assessed",IF(M8>=4,"Compliant",IF(M8>=3,"Substantially compliant",IF(M8>=2,"Partially compliant","Non-compliant")))))) | P8: =IF(N8=0,"",F8*(4-M8)) | Q8: =IF(P8="","",IF(P8>=12,"Critical",IF(P8>=8,"High",IF(P8>=4,"Medium",IF(P8>=1,"Low","None"))))) | R8: =IF(AND(N8=1,M8<3),1,0) | S8: =IF(N8=0,"",M8*G8) | T8: =IF(N8=0,"",4*G8) | U8: A record of processing activities exists in a spreadsheet covering 61 activities, last updated November 2025. Walkthroughs identified four unrecorded processing activities: Kavach Junior parent supervision, the WhatsApp collections journey, the churn-prediction model in Kavach Analytics, and employee productivity monitoring in the collections function. The record does not capture retention period or recipient for 23 of the 61 entries. | V8: WP-011 | W8: Meera Raghunathan, Head of Legal & Compliance | Y8: Although the Act does not name a register in terms, the burden of demonstrating consent under section 6(10) and the accountability duty under section 8(1) cannot be discharged without a reliable record of what personal data is processed, for what purpose, on what basis, and with whom it is shared. | Z8: Is there a complete, current record of processing activities capturing data categories, purposes, lawful basis, retention, recipients, processors and cross-border flows? Is it reconciled to reality rather than maintained as a one-off documentation exercise? | AA8: Inspect the register; test completeness by selecting two systems not obviously covered and tracing them; test currency against recent product changes. | AB8: Record of processing activities with the fields above · Evidence of periodic review with dates and reviewer · Reconciliation to a system or application inventory | AC8: Up to INR 50 crore | AD8: 7 | AE8: A complete register is reconciled to the application inventory, refreshed on a defined cycle and on material change, and demonstrably drives downstream artefacts such as notices and retention rules.
A9: GOV-03 | B9: GOV | C9: Governance, Accountability & Records | D9: Publication of DPO or contact person details | E9: High | F9: =IF(E9="Critical",4,IF(E9="High",3,IF(E9="Medium",2,1))) | G9: 1 | H9: Yes | I9: in scope | J9: s.8(8), DPDP Act, 2023 | K9: [Rules citation to be verified] | L9: VERIFY_AGAINST_NOTIFIED_RULES | M9: 3 | N9: =IF(OR(H9="No",M9="",UPPER(M9)="NA"),0,1) | O9: =IF(H9="No","Out of scope",IF(UPPER(M9)="NA","Not applicable",IF(M9="","Not assessed",IF(M9>=4,"Compliant",IF(M9>=3,"Substantially compliant",IF(M9>=2,"Partially compliant","Non-compliant")))))) | P9: =IF(N9=0,"",F9*(4-M9)) | Q9: =IF(P9="","",IF(P9>=12,"Critical",IF(P9>=8,"High",IF(P9>=4,"Medium",IF(P9>=1,"Low","None"))))) | R9: =IF(AND(N9=1,M9<3),1,0) | S9: =IF(N9=0,"",M9*G9) | T9: =IF(N9=0,"",4*G9) | U9: Contact details for the privacy function are published in the app privacy policy and on the website footer, and the address routes to a monitored mailbox. The published contact is a generic role address rather than the person discharging the function, and the Kavach Junior parent console does not surface the contact at all. | V9: WP-012 | W9: Meera Raghunathan, Head of Legal & Compliance | Y9: A Data Fiduciary must publish the business contact information of the Data Protection Officer, if applicable, or of a person able to answer on its behalf the questions of a Data Principal about the processing of their personal data. | Z9: Are contact details published in a place a Data Principal would actually find them, and does a real, monitored channel sit behind them that is capable of answering substantive questions about processing? | AA9: Inspect the published details on all customer-facing surfaces; re-perform by sending a substantive processing question through the channel and measuring the response. | AB9: Screenshots of published contact details on website, app and other surfaces · Evidence of channel monitoring and ownership · Sample of substantive questions received and answered | AC9: Up to INR 50 crore | AD9: 7 | AE9: Details are prominently and consistently published across all surfaces, the channel is monitored with defined ownership and service levels, and testing shows substantive questions are answered competently.
A10: GOV-04 | B10: GOV | C10: Governance, Accountability & Records | D10: Board and senior management oversight | E10: Medium | F10: =IF(E10="Critical",4,IF(E10="High",3,IF(E10="Medium",2,1))) | G10: 1 | H10: Yes | I10: in scope | J10: s.8(1), s.10(2)(a), DPDP Act, 2023 | K10: — | L10: — | M10: 2 | N10: =IF(OR(H10="No",M10="",UPPER(M10)="NA"),0,1) | O10: =IF(H10="No","Out of scope",IF(UPPER(M10)="NA","Not applicable",IF(M10="","Not assessed",IF(M10>=4,"Compliant",IF(M10>=3,"Substantially compliant",IF(M10>=2,"Partially compliant","Non-compliant")))))) | P10: =IF(N10=0,"",F10*(4-M10)) | Q10: =IF(P10="","",IF(P10>=12,"Critical",IF(P10>=8,"High",IF(P10>=4,"Medium",IF(P10>=1,"Low","None"))))) | R10: =IF(AND(N10=1,M10<3),1,0) | S10: =IF(N10=0,"",M10*G10) | T10: =IF(N10=0,"",4*G10) | U10: Privacy is reported to the Risk Management Committee twice yearly as part of a combined information security update. Minutes for the two meetings in the period record no privacy-specific decision, no budget approval and no challenge from members. There is no board-level acceptance of the residual risk arising from the open items in this report. | V10: WP-013 | W10: Vikram Shetty, Chief Financial Officer | Y10: Accountability under section 8(1) requires oversight proportionate to the risk. For a Significant Data Fiduciary the Data Protection Officer is expressly required to be responsible to the board of directors or similar governing body, which sets the expected standard of engagement. | Z10: Does the board or an equivalent governing body receive periodic reporting on data protection risk, breaches, rights-request volumes and remediation progress, and is there evidence of it directing action? | AA10: Inspect minutes and reporting packs for the last four cycles; test whether reported issues were tracked to closure. | AB10: Board or committee minutes referencing data protection matters · Management information pack showing metrics reported · Evidence of decisions taken and tracked to closure | AC10: — | AE10: Periodic reporting on a defined cycle with meaningful metrics, evidenced challenge from the forum, and issues tracked to closure.
A11: GOV-05 | B11: GOV | C11: Governance, Accountability & Records | D11: Policies, standards and internal procedures | E11: Medium | F11: =IF(E11="Critical",4,IF(E11="High",3,IF(E11="Medium",2,1))) | G11: 1 | H11: Yes | I11: in scope | J11: s.8(4), DPDP Act, 2023 | K11: — | L11: — | M11: 3 | N11: =IF(OR(H11="No",M11="",UPPER(M11)="NA"),0,1) | O11: =IF(H11="No","Out of scope",IF(UPPER(M11)="NA","Not applicable",IF(M11="","Not assessed",IF(M11>=4,"Compliant",IF(M11>=3,"Substantially compliant",IF(M11>=2,"Partially compliant","Non-compliant")))))) | P11: =IF(N11=0,"",F11*(4-M11)) | Q11: =IF(P11="","",IF(P11>=12,"Critical",IF(P11>=8,"High",IF(P11>=4,"Medium",IF(P11>=1,"Low","None"))))) | R11: =IF(AND(N11=1,M11<3),1,0) | S11: =IF(N11=0,"",M11*G11) | T11: =IF(N11=0,"",4*G11) | U11: A policy set comprising an Information Privacy Policy, Data Classification Standard, Retention Standard and Third Party Standard is approved and accessible on the intranet. The Retention Standard is dated 2023 and predates both the Kavach Junior product and the current warehouse architecture, and the Third Party Standard does not address the s.8(2) contract requirement. | V11: WP-014 | W11: Meera Raghunathan, Head of Legal & Compliance | Y11: Appropriate technical and organisational measures under section 8(4) include the documented policies and procedures by which the entity gives effect to its obligations. | Z11: Is there an approved policy set covering notice, consent, rights handling, retention, breach response, vendor management and children's data, mapped to the Act, version-controlled and actually reflected in operational procedure? | AA11: Inspect the policy set and approval records; test one policy against the operational procedure and system behaviour it purports to govern. | AB11: Approved policy set with version history and approver · Mapping of policies to Act provisions · Operational procedures or runbooks referenced by the policies | AC11: Up to INR 50 crore | AD11: 7 | AE11: An approved, version-controlled, Act-mapped policy set is in force, supported by operational runbooks, and testing confirms practice follows the documented procedure.
A12: GOV-06 | B12: GOV | C12: Governance, Accountability & Records | D12: Training and awareness | E12: Medium | F12: =IF(E12="Critical",4,IF(E12="High",3,IF(E12="Medium",2,1))) | G12: 0.9 | H12: Yes | I12: in scope | J12: s.8(4), DPDP Act, 2023 | K12: — | L12: — | M12: 2 | N12: =IF(OR(H12="No",M12="",UPPER(M12)="NA"),0,1) | O12: =IF(H12="No","Out of scope",IF(UPPER(M12)="NA","Not applicable",IF(M12="","Not assessed",IF(M12>=4,"Compliant",IF(M12>=3,"Substantially compliant",IF(M12>=2,"Partially compliant","Non-compliant")))))) | P12: =IF(N12=0,"",F12*(4-M12)) | Q12: =IF(P12="","",IF(P12>=12,"Critical",IF(P12>=8,"High",IF(P12>=4,"Medium",IF(P12>=1,"Low","None"))))) | R12: =IF(AND(N12=1,M12<3),1,0) | S12: =IF(N12=0,"",M12*G12) | T12: =IF(N12=0,"",4*G12) | U12: Annual information security training is mandatory and completion stands at 94 per cent. Privacy content within it runs to four slides and does not address consent, rights handling or the children's provisions. No role-specific training has been delivered to the engineering, marketing or collections teams whose decisions determine compliance in practice. | V12: WP-015 | W12: Sneha Kulkarni, Head of People | Y12: Organisational measures under section 8(4) extend to ensuring that personnel handling personal data understand their obligations, particularly those operating consent, rights and breach processes. | Z12: Have personnel in roles that touch personal data received DPDPA-specific training, with role-tailored content for high-risk functions such as support, marketing, engineering and procurement, and is completion tracked? | AA12: Inspect training content and completion records; enquire of a sample of staff in high-risk roles to test practical understanding. | AB12: Training material specific to the Act, not generic privacy content · Completion records by role with dates · Role-specific modules for support, marketing, engineering and procurement | AC12: — | AE12: Act-specific training is delivered to all relevant personnel with role-tailored modules for high-risk functions, completion is tracked and enforced, and sample enquiry confirms practical understanding.
A13: GOV-07 | B13: GOV | C13: Governance, Accountability & Records | D13: Evidence retention for demonstrating compliance | E13: Critical | F13: =IF(E13="Critical",4,IF(E13="High",3,IF(E13="Medium",2,1))) | G13: 1.2 | H13: Yes | I13: in scope | J13: s.6(10), DPDP Act, 2023 | K13: — | L13: — | M13: 1 | N13: =IF(OR(H13="No",M13="",UPPER(M13)="NA"),0,1) | O13: =IF(H13="No","Out of scope",IF(UPPER(M13)="NA","Not applicable",IF(M13="","Not assessed",IF(M13>=4,"Compliant",IF(M13>=3,"Substantially compliant",IF(M13>=2,"Partially compliant","Non-compliant")))))) | P13: =IF(N13=0,"",F13*(4-M13)) | Q13: =IF(P13="","",IF(P13>=12,"Critical",IF(P13>=8,"High",IF(P13>=4,"Medium",IF(P13>=1,"Low","None"))))) | R13: =IF(AND(N13=1,M13<3),1,0) | S13: =IF(N13=0,"",M13*G13) | T13: =IF(N13=0,"",4*G13) | U13: Evidence of compliance is not systematically retained. Consent artefacts are held only in the current state of the consent table with no immutable history, notice versions are not archived, and rights request correspondence is held in agent mailboxes. The entity could not reconstruct, for a Data Principal who consented in March 2025, what notice they were shown. This directly undermines the ability to discharge the burden of proof the Act places on the Data Fiduciary. | V13: WP-016 | W13: Devika Iyer, VP Engineering | Y13: Where consent is relied upon, the Data Fiduciary bears the burden of proving that notice was given and consent was obtained in accordance with the Act. This requires retention of the underlying artefacts, not merely of the current policy. | Z13: Can the entity produce, for a Data Principal selected at random, the notice text as presented at the time, the consent artefact, and the processing history — or can it only produce today's policy? | AA13: Re-perform: select two Data Principals at random and require production of the historical notice version, consent artefact and processing record. | AB13: Versioned archive of notice and consent text with effective dates · Consent artefacts retrievable per Data Principal · Documented evidence retention period aligned to limitation and inquiry risk | AC13: Up to INR 50 crore | AD13: 7 | AE13: Notice versions and consent artefacts are archived and jointly retrievable per Data Principal, and testing confirms the entity can reconstruct precisely what was presented and agreed to, and when.
A14: PUR-01 | B14: PUR | C14: Lawful Purpose, Minimisation & Accuracy | D14: Every processing activity has an identified lawful basis | E14: Critical | F14: =IF(E14="Critical",4,IF(E14="High",3,IF(E14="Medium",2,1))) | G14: 1.3 | H14: Yes | I14: in scope | J14: s.4(1), s.4(2), DPDP Act, 2023 | K14: — | L14: — | M14: 2 | N14: =IF(OR(H14="No",M14="",UPPER(M14)="NA"),0,1) | O14: =IF(H14="No","Out of scope",IF(UPPER(M14)="NA","Not applicable",IF(M14="","Not assessed",IF(M14>=4,"Compliant",IF(M14>=3,"Substantially compliant",IF(M14>=2,"Partially compliant","Non-compliant")))))) | P14: =IF(N14=0,"",F14*(4-M14)) | Q14: =IF(P14="","",IF(P14>=12,"Critical",IF(P14>=8,"High",IF(P14>=4,"Medium",IF(P14>=1,"Low","None"))))) | R14: =IF(AND(N14=1,M14<3),1,0) | S14: =IF(N14=0,"",M14*G14) | T14: =IF(N14=0,"",4*G14) | U14: A lawful basis is documented for the lending and payments journeys. Four activities have no identified basis: the churn model, marketing enrichment from a third-party data broker, call recording in collections, and the employee monitoring noted at GOV-02. Management's position that these fall within 'legitimate business interest' has no counterpart in the Act, which provides a closed list of legitimate uses. | V14: WP-020 | W14: Meera Raghunathan, Head of Legal & Compliance | Y14: Personal data may be processed only for a lawful purpose for which the Data Principal has given consent, or for a certain legitimate use. A lawful purpose is one not expressly forbidden by law. | Z14: Is a specific lawful basis — consent or a named section 7 legitimate use — recorded for every processing activity in the register, with no activity left unmapped or resting on a basis that does not exist under the Act? | AA14: Inspect basis mapping for completeness; re-perform the determination for a sample of five activities, including at least one marketing and one analytics use. | AB14: Lawful basis recorded per activity in the processing register · Reasoning for each legitimate use relied upon, citing the specific limb · Evidence that no activity relies on a ground absent from the Act | AC14: Up to INR 50 crore | AD14: 7 | AE14: Every activity carries a specific, documented and defensible basis citing the exact provision, reviewed on change, with no reliance on grounds the Act does not contain.
A15: PUR-02 | B15: PUR | C15: Lawful Purpose, Minimisation & Accuracy | D15: Data minimisation — collection limited to what is necessary | E15: High | F15: =IF(E15="Critical",4,IF(E15="High",3,IF(E15="Medium",2,1))) | G15: 1.2 | H15: Yes | I15: in scope | J15: s.6(1), s.6(2), DPDP Act, 2023 | K15: — | L15: — | M15: 2 | N15: =IF(OR(H15="No",M15="",UPPER(M15)="NA"),0,1) | O15: =IF(H15="No","Out of scope",IF(UPPER(M15)="NA","Not applicable",IF(M15="","Not assessed",IF(M15>=4,"Compliant",IF(M15>=3,"Substantially compliant",IF(M15>=2,"Partially compliant","Non-compliant")))))) | P15: =IF(N15=0,"",F15*(4-M15)) | Q15: =IF(P15="","",IF(P15>=12,"Critical",IF(P15>=8,"High",IF(P15>=4,"Medium",IF(P15>=1,"Low","None"))))) | R15: =IF(AND(N15=1,M15<3),1,0) | S15: =IF(N15=0,"",M15*G15) | T15: =IF(N15=0,"",4*G15) | U15: The onboarding journey collects marital status, education level and employer address for all applicants irrespective of product. Product management confirmed these fields are used only for a subset of underwriting models and could not evidence necessity for the payments-only journey, which represents roughly 60 per cent of registrations. | V15: WP-021 | W15: Rohit Menon, Head of Product | Y15: Consent signifies agreement to processing of only such personal data as is necessary for the specified purpose, and any part of consent that purports to extend beyond that is invalid to that extent. | Z15: For each collection point, is every field necessary for the stated purpose? Are optional fields distinguished from mandatory ones, and has any field been challenged and removed as a result of review? | AA15: Inspect a sample of collection forms and API payloads field by field against stated purposes; test whether mandatory fields are genuinely necessary. | AB15: Field-level necessity analysis for principal collection points · Distinction between mandatory and optional fields in the interface · Change records showing fields removed following review | AC15: Up to INR 50 crore | AD15: 7 | AE15: Field-level necessity is documented and periodically re-tested, optional fields are clearly distinguished, and there is evidence of fields having actually been removed as unnecessary.
A16: PUR-03 | B16: PUR | C16: Lawful Purpose, Minimisation & Accuracy | D16: Purpose limitation — no undisclosed secondary use | E16: High | F16: =IF(E16="Critical",4,IF(E16="High",3,IF(E16="Medium",2,1))) | G16: 1.2 | H16: Yes | I16: in scope | J16: s.4(1), s.5(1), s.6(1), DPDP Act, 2023 | K16: — | L16: — | M16: 1 | N16: =IF(OR(H16="No",M16="",UPPER(M16)="NA"),0,1) | O16: =IF(H16="No","Out of scope",IF(UPPER(M16)="NA","Not applicable",IF(M16="","Not assessed",IF(M16>=4,"Compliant",IF(M16>=3,"Substantially compliant",IF(M16>=2,"Partially compliant","Non-compliant")))))) | P16: =IF(N16=0,"",F16*(4-M16)) | Q16: =IF(P16="","",IF(P16>=12,"Critical",IF(P16>=8,"High",IF(P16>=4,"Medium",IF(P16>=1,"Low","None"))))) | R16: =IF(AND(N16=1,M16<3),1,0) | S16: =IF(N16=0,"",M16*G16) | T16: =IF(N16=0,"",4*G16) | U16: Transaction data collected for payments processing is used to build propensity segments that are pushed to Meta and Google for acquisition campaigns. The notice presented at registration does not disclose advertising as a purpose. This is undisclosed secondary use of data obtained for a different specified purpose. | V16: WP-022 | W16: Rohit Menon, Head of Product | Y16: Processing must be for the specified purpose for which consent was given. Personal data may not be repurposed for materially different uses without a fresh lawful basis. | Z16: Are there controls preventing personal data collected for one purpose being used for another — particularly transaction data flowing into marketing, or customer data into model training — and is a fresh basis obtained where the purpose is materially new? | AA16: Inspect data flows from primary systems into analytics, marketing and machine-learning environments; test each against the notice given at collection. | AB16: Data flow documentation from collection into secondary environments · Purpose-compatibility assessments for secondary uses · Evidence of fresh notice and consent where purposes were materially extended | AC16: Up to INR 50 crore | AD16: 7 | AE16: Secondary use is gated by documented compatibility assessment, technically constrained where possible, and fresh notice and consent are obtained for materially new purposes with evidence of the gate having been enforced.
A17: PUR-04 | B17: PUR | C17: Lawful Purpose, Minimisation & Accuracy | D17: Accuracy and completeness where data drives decisions or is shared | E17: High | F17: =IF(E17="Critical",4,IF(E17="High",3,IF(E17="Medium",2,1))) | G17: 1.1 | H17: Yes | I17: in scope | J17: s.8(3), DPDP Act, 2023 | K17: — | L17: — | M17: 3 | N17: =IF(OR(H17="No",M17="",UPPER(M17)="NA"),0,1) | O17: =IF(H17="No","Out of scope",IF(UPPER(M17)="NA","Not applicable",IF(M17="","Not assessed",IF(M17>=4,"Compliant",IF(M17>=3,"Substantially compliant",IF(M17>=2,"Partially compliant","Non-compliant")))))) | P17: =IF(N17=0,"",F17*(4-M17)) | Q17: =IF(P17="","",IF(P17>=12,"Critical",IF(P17>=8,"High",IF(P17>=4,"Medium",IF(P17>=1,"Low","None"))))) | R17: =IF(AND(N17=1,M17<3),1,0) | S17: =IF(N17=0,"",M17*G17) | T17: =IF(N17=0,"",4*G17) | U17: Bureau and KYC data feeding underwriting is refreshed at decision time and a correction workflow exists in Kavach CRM. Corrections applied in CRM do not propagate to the Snowflake warehouse, so models and collections lists may run on superseded data for up to 30 days. | V17: WP-023 | W17: Devika Iyer, VP Engineering | Y17: Where personal data is likely to be used to make a decision affecting the Data Principal, or is likely to be disclosed to another Data Fiduciary, the Data Fiduciary must ensure it is complete, accurate and consistent. | Z17: Has the entity identified which processing produces decisions affecting Data Principals or involves disclosure onward, and what controls assure accuracy, completeness and consistency in those specific flows? | AA17: Inspect the inventory of decisioning and disclosure flows; test accuracy controls including validation, reconciliation and correction propagation in a sample flow. | AB17: Inventory of decision-making and onward-disclosure flows · Data quality controls: validation rules, reconciliation, exception handling · Evidence that corrections propagate to downstream recipients and decisions | AC17: Up to INR 50 crore | AD17: 7 | AE17: Decisioning and disclosure flows are inventoried, subject to defined accuracy and consistency controls, and corrections demonstrably propagate downstream with evidence of exception handling.
A18: PUR-05 | B18: PUR | C18: Lawful Purpose, Minimisation & Accuracy | D18: Privacy considered at design stage for new processing | E18: Medium | F18: =IF(E18="Critical",4,IF(E18="High",3,IF(E18="Medium",2,1))) | G18: 1 | H18: Yes | I18: in scope | J18: s.8(4), DPDP Act, 2023 | K18: — | L18: — | M18: 2 | N18: =IF(OR(H18="No",M18="",UPPER(M18)="NA"),0,1) | O18: =IF(H18="No","Out of scope",IF(UPPER(M18)="NA","Not applicable",IF(M18="","Not assessed",IF(M18>=4,"Compliant",IF(M18>=3,"Substantially compliant",IF(M18>=2,"Partially compliant","Non-compliant")))))) | P18: =IF(N18=0,"",F18*(4-M18)) | Q18: =IF(P18="","",IF(P18>=12,"Critical",IF(P18>=8,"High",IF(P18>=4,"Medium",IF(P18>=1,"Low","None"))))) | R18: =IF(AND(N18=1,M18<3),1,0) | S18: =IF(N18=0,"",M18*G18) | T18: =IF(N18=0,"",4*G18) | U18: A privacy review is a documented gate in the product development lifecycle but is discretionary in practice. Of the 11 features released in the period, three carried a completed review. Kavach Junior, the highest-risk launch in the period, went live without one. | V18: WP-024 | W18: Rohit Menon, Head of Product | Y18: Appropriate technical and organisational measures under section 8(4) require that new products, features and vendor engagements are assessed for compliance before personal data is processed, not after. | Z18: Is there a gate in the product and procurement lifecycle requiring privacy assessment before launch, and is there evidence of it having actually blocked or changed a launch? | AA18: Inspect the gate definition and completed assessments; test a sample of recent launches for whether the gate was applied before go-live. | AB18: Defined assessment gate in the product and procurement lifecycle · Completed assessments for recent launches, dated before go-live · Evidence of at least one launch changed or blocked as a result | AC18: — | AE18: The gate is embedded and enforced before go-live, with completed assessments predating launch and evidence of launches having been changed or blocked on privacy grounds.
A19: NOT-01 | B19: NOT | C19: Notice | D19: Notice accompanies or precedes every consent request | E19: Critical | F19: =IF(E19="Critical",4,IF(E19="High",3,IF(E19="Medium",2,1))) | G19: 1.3 | H19: Yes | I19: in scope | J19: s.5(1)(i), DPDP Act, 2023 | K19: [Rules citation to be verified] | L19: VERIFY_AGAINST_NOTIFIED_RULES | M19: 3 | N19: =IF(OR(H19="No",M19="",UPPER(M19)="NA"),0,1) | O19: =IF(H19="No","Out of scope",IF(UPPER(M19)="NA","Not applicable",IF(M19="","Not assessed",IF(M19>=4,"Compliant",IF(M19>=3,"Substantially compliant",IF(M19>=2,"Partially compliant","Non-compliant")))))) | P19: =IF(N19=0,"",F19*(4-M19)) | Q19: =IF(P19="","",IF(P19>=12,"Critical",IF(P19>=8,"High",IF(P19>=4,"Medium",IF(P19>=1,"Low","None"))))) | R19: =IF(AND(N19=1,M19<3),1,0) | S19: =IF(N19=0,"",M19*G19) | T19: =IF(N19=0,"",4*G19) | U19: The registration journey presents a notice screen before the consent action on the mobile application. In the web journey and in the assisted onboarding flow used by field agents, the notice is presented as a hyperlink beside a pre-ticked declaration, so it neither accompanies nor precedes the consent in any meaningful sense. | V19: WP-030 | W19: Rohit Menon, Head of Product | Y19: Every request for consent must be accompanied or preceded by a notice informing the Data Principal of the personal data to be processed and the purpose of processing. | Z19: At every consent collection point, is a notice presented at or before the moment of consent — as distinct from a hyperlink to a privacy policy sitting beside a pre-ticked box? | AA19: Observation: walk every consent journey — web, app, offline, telephonic, partner-led — and record what is presented at the moment of consent. | AB19: Screenshots or recordings of each consent journey showing notice placement · Inventory of all consent collection points including offline and partner channels · Notice text as presented, not merely the policy it links to | AC19: Up to INR 50 crore | AD19: 7 | AE19: A compliant notice is presented at or before consent on every channel, with an inventory demonstrating completeness and periodic re-walking of journeys to confirm.
A20: NOT-02 | B20: NOT | C20: Notice | D20: Notice content — itemised data and specified purpose | E20: Critical | F20: =IF(E20="Critical",4,IF(E20="High",3,IF(E20="Medium",2,1))) | G20: 1.3 | H20: Yes | I20: in scope | J20: s.5(1)(i), DPDP Act, 2023 | K20: [Rules citation to be verified] | L20: VERIFY_AGAINST_NOTIFIED_RULES | M20: 1 | N20: =IF(OR(H20="No",M20="",UPPER(M20)="NA"),0,1) | O20: =IF(H20="No","Out of scope",IF(UPPER(M20)="NA","Not applicable",IF(M20="","Not assessed",IF(M20>=4,"Compliant",IF(M20>=3,"Substantially compliant",IF(M20>=2,"Partially compliant","Non-compliant")))))) | P20: =IF(N20=0,"",F20*(4-M20)) | Q20: =IF(P20="","",IF(P20>=12,"Critical",IF(P20>=8,"High",IF(P20>=4,"Medium",IF(P20>=1,"Low","None"))))) | R20: =IF(AND(N20=1,M20<3),1,0) | S20: =IF(N20=0,"",M20*G20) | T20: =IF(N20=0,"",4*G20) | U20: The notice describes the data collected in categories such as 'identity and contact information' and 'usage data' and states purposes as 'to provide and improve our services'. It is neither an itemised description of the personal data nor a specified purpose. The notice also omits the account aggregator data received through the Consent Manager entirely. | V20: WP-031 | W20: Meera Raghunathan, Head of Legal & Compliance | Y20: The notice must inform the Data Principal of the personal data proposed to be processed and the purpose of such processing. | Z20: Does the notice itemise the actual categories of personal data and state specific purposes, or does it use open-ended formulations such as "information you provide" and "to improve our services"? | AA20: Inspect notice text against the processing register; test whether every category and purpose in the register appears in the notice and vice versa. | AB20: Notice text with itemised data categories and specific purposes · Reconciliation of notice content to the processing register · Absence of catch-all purpose language | AC20: Up to INR 50 crore | AD20: 7 | AE20: Notice itemises data categories and states each purpose specifically, reconciles to the register in both directions, and is updated when processing changes.
A21: NOT-03 | B21: NOT | C21: Notice | D21: Notice explains rights and the route to the Board | E21: High | F21: =IF(E21="Critical",4,IF(E21="High",3,IF(E21="Medium",2,1))) | G21: 1.2 | H21: Yes | I21: in scope | J21: s.5(1)(ii), s.5(1)(iii), DPDP Act, 2023 | K21: [Rules citation to be verified] | L21: VERIFY_AGAINST_NOTIFIED_RULES | M21: 2 | N21: =IF(OR(H21="No",M21="",UPPER(M21)="NA"),0,1) | O21: =IF(H21="No","Out of scope",IF(UPPER(M21)="NA","Not applicable",IF(M21="","Not assessed",IF(M21>=4,"Compliant",IF(M21>=3,"Substantially compliant",IF(M21>=2,"Partially compliant","Non-compliant")))))) | P21: =IF(N21=0,"",F21*(4-M21)) | Q21: =IF(P21="","",IF(P21>=12,"Critical",IF(P21>=8,"High",IF(P21>=4,"Medium",IF(P21>=1,"Low","None"))))) | R21: =IF(AND(N21=1,M21<3),1,0) | S21: =IF(N21=0,"",M21*G21) | T21: =IF(N21=0,"",4*G21) | U21: The notice explains the access and correction rights and links to the grievance form. It does not explain the right to withdraw consent, the right to nominate, or the manner in which a Data Principal may make a complaint to the Data Protection Board. | V21: WP-032 | W21: Meera Raghunathan, Head of Legal & Compliance | Y21: The notice must inform the Data Principal of the manner in which they may exercise their rights to withdraw consent and to grievance redressal, and of the manner in which a complaint may be made to the Data Protection Board. | Z21: Does the notice explain, in operative terms, how to withdraw consent, how to seek grievance redressal, and how to complain to the Board — including the fact that the grievance mechanism must be exhausted first? | AA21: Inspect notice text for each of the three disclosures; test that the mechanisms described actually work as stated. | AB21: Notice text covering withdrawal, grievance redressal and complaint to the Board · Working links or contact routes for each · Consistency between what the notice describes and the operative mechanism | AC21: Up to INR 50 crore | AD21: 7 | AE21: All three are disclosed with operative, tested routes, and the notice correctly explains the sequencing of grievance redressal before approach to the Board.
A22: NOT-04 | B22: NOT | C22: Notice | D22: Notice available in English and Eighth Schedule languages | E22: Medium | F22: =IF(E22="Critical",4,IF(E22="High",3,IF(E22="Medium",2,1))) | G22: 1 | H22: Yes | I22: in scope | J22: s.5(3), DPDP Act, 2023 | K22: [Rules citation to be verified] | L22: VERIFY_AGAINST_NOTIFIED_RULES | M22: 1 | N22: =IF(OR(H22="No",M22="",UPPER(M22)="NA"),0,1) | O22: =IF(H22="No","Out of scope",IF(UPPER(M22)="NA","Not applicable",IF(M22="","Not assessed",IF(M22>=4,"Compliant",IF(M22>=3,"Substantially compliant",IF(M22>=2,"Partially compliant","Non-compliant")))))) | P22: =IF(N22=0,"",F22*(4-M22)) | Q22: =IF(P22="","",IF(P22>=12,"Critical",IF(P22>=8,"High",IF(P22>=4,"Medium",IF(P22>=1,"Low","None"))))) | R22: =IF(AND(N22=1,M22<3),1,0) | S22: =IF(N22=0,"",M22*G22) | T22: =IF(N22=0,"",4*G22) | U22: Notice and consent screens are available in English and Hindi only. The entity's own registration data shows material user populations in Tamil, Telugu, Marathi, Bengali and Kannada. No language other than English and Hindi is offered, and no request mechanism exists for the remaining Eighth Schedule languages. | V22: WP-033 | W22: Rohit Menon, Head of Product | Y22: The Data Principal must be given the option to access the notice in English or any language specified in the Eighth Schedule to the Constitution of India. | Z22: Is the notice actually available in English and in Eighth Schedule languages, with a discoverable language selector — and are the translations accurate rather than machine-rendered approximations of legal effect? | AA22: Observation: locate and exercise the language option on each surface; inspect translation provenance and review process. | AB22: Notice published in English plus Eighth Schedule languages · Discoverable language selection mechanism on each surface · Translation review or certification records | AC22: Up to INR 50 crore | AD22: 7 | AE22: The option is genuinely available and discoverable across surfaces, translations are reviewed for legal accuracy, and version control keeps every language aligned when the notice changes.
A23: NOT-05 | B23: NOT | C23: Notice | D23: Retrospective notice for pre-commencement consent | E23: High | F23: =IF(E23="Critical",4,IF(E23="High",3,IF(E23="Medium",2,1))) | G23: 1.1 | H23: Yes | I23: in scope | J23: s.5(2), DPDP Act, 2023 | K23: [Rules citation to be verified] | L23: VERIFY_AGAINST_NOTIFIED_RULES | M23: 0 | N23: =IF(OR(H23="No",M23="",UPPER(M23)="NA"),0,1) | O23: =IF(H23="No","Out of scope",IF(UPPER(M23)="NA","Not applicable",IF(M23="","Not assessed",IF(M23>=4,"Compliant",IF(M23>=3,"Substantially compliant",IF(M23>=2,"Partially compliant","Non-compliant")))))) | P23: =IF(N23=0,"",F23*(4-M23)) | Q23: =IF(P23="","",IF(P23>=12,"Critical",IF(P23>=8,"High",IF(P23>=4,"Medium",IF(P23>=1,"Low","None"))))) | R23: =IF(AND(N23=1,M23<3),1,0) | S23: =IF(N23=0,"",M23*G23) | T23: =IF(N23=0,"",4*G23) | U23: Approximately 9.4 million Data Principals onboarded before the current notice version have not been given a retrospective notice. Management was aware of the requirement and has scoped a campaign but has not set a date, citing concern about attrition and support volume. No compensating action has been taken. | V23: WP-034 | W23: Meera Raghunathan, Head of Legal & Compliance | Y23: Where personal data is processed on the basis of consent given before the commencement of the Act, the Data Fiduciary must, as soon as reasonably practicable, give the Data Principal a notice compliant with the Act's requirements. Processing may continue until consent is withdrawn. | Z23: Has the entity identified its pre-commencement consent population and issued compliant retrospective notice to it, with evidence of despatch and of handling the withdrawals that follow? | AA23: Inspect the identified population and despatch evidence; test a sample of records for whether notice was in fact issued and what followed. | AB23: Identification of the pre-commencement Data Principal population · Notice content issued retrospectively and despatch records · Handling of withdrawals arising from the exercise | AC23: Up to INR 50 crore | AD23: 7 | AE23: The full population is identified, compliant notice is evidenced as despatched, coverage gaps are documented with rationale, and resulting withdrawals were processed and evidenced.
A24: CON-01 | B24: CON | C24: Consent | D24: Consent is free, specific, informed, unconditional and unambiguous | E24: Critical | F24: =IF(E24="Critical",4,IF(E24="High",3,IF(E24="Medium",2,1))) | G24: 1.4 | H24: Yes | I24: in scope | J24: s.6(1), DPDP Act, 2023 | K24: [Rules citation to be verified] | L24: VERIFY_AGAINST_NOTIFIED_RULES | M24: 2 | N24: =IF(OR(H24="No",M24="",UPPER(M24)="NA"),0,1) | O24: =IF(H24="No","Out of scope",IF(UPPER(M24)="NA","Not applicable",IF(M24="","Not assessed",IF(M24>=4,"Compliant",IF(M24>=3,"Substantially compliant",IF(M24>=2,"Partially compliant","Non-compliant")))))) | P24: =IF(N24=0,"",F24*(4-M24)) | Q24: =IF(P24="","",IF(P24>=12,"Critical",IF(P24>=8,"High",IF(P24>=4,"Medium",IF(P24>=1,"Low","None"))))) | R24: =IF(AND(N24=1,M24<3),1,0) | S24: =IF(N24=0,"",M24*G24) | T24: =IF(N24=0,"",4*G24) | U24: Consent is captured through a single checkbox covering the privacy policy, terms of service, marketing communications and credit bureau enquiry. It is therefore neither specific nor unconditional: a Data Principal cannot accept the service without also accepting marketing. Purpose-level granularity exists in the data model but is not exposed in the interface. | V24: WP-040 | W24: Rohit Menon, Head of Product | Y24: Consent must be free, specific, informed, unconditional and unambiguous with a clear affirmative action, signifying agreement to processing of the personal data for the specified purpose. | Z24: Does each consent involve a clear affirmative action — no pre-ticked boxes, no consent inferred from continued use, no consent bundled across unrelated purposes into a single acceptance? | AA24: Observation and re-performance: complete each consent journey and record the mechanism; inspect the stored artefact to confirm it reflects an affirmative act. | AB24: Consent interface showing unticked, separate, affirmative controls · Absence of consent inferred from silence, inactivity or continued use · Separate consent per distinct purpose | AC24: Up to INR 50 crore | AD24: 7 | AE24: Each distinct purpose has its own unticked affirmative control, no consent is inferred from inactivity, and the stored artefact records which specific purposes were agreed.
A25: CON-02 | B25: CON | C25: Consent | D25: Consent not conditioned on service where data is unnecessary | E25: Critical | F25: =IF(E25="Critical",4,IF(E25="High",3,IF(E25="Medium",2,1))) | G25: 1.3 | H25: Yes | I25: in scope | J25: s.6(1), s.6(2), DPDP Act, 2023 | K25: — | L25: — | M25: 2 | N25: =IF(OR(H25="No",M25="",UPPER(M25)="NA"),0,1) | O25: =IF(H25="No","Out of scope",IF(UPPER(M25)="NA","Not applicable",IF(M25="","Not assessed",IF(M25>=4,"Compliant",IF(M25>=3,"Substantially compliant",IF(M25>=2,"Partially compliant","Non-compliant")))))) | P25: =IF(N25=0,"",F25*(4-M25)) | Q25: =IF(P25="","",IF(P25>=12,"Critical",IF(P25>=8,"High",IF(P25>=4,"Medium",IF(P25>=1,"Low","None"))))) | R25: =IF(AND(N25=1,M25<3),1,0) | S25: =IF(N25=0,"",M25*G25) | T25: =IF(N25=0,"",4*G25) | U25: Registration for the payments-only product cannot be completed without consenting to the bureau enquiry, which is not necessary for that service. The lending journey, by contrast, is correctly scoped. | V25: WP-041 | W25: Rohit Menon, Head of Product | Y25: Consent extends only to personal data necessary for the specified purpose, and is invalid to the extent it purports to go further. Consent conditioned on provision of unnecessary data is not free. | Z25: Is access to the service made conditional on consent to processing that is not necessary for delivering it — marketing, profiling, enrichment or data sharing presented as unavoidable? | AA25: Re-performance: attempt to complete onboarding declining every non-essential consent, and record whether the service remains usable. | AB25: Evidence that the service functions when non-essential consents are declined · Analysis distinguishing necessary from optional processing per service · Absence of dark patterns making refusal disproportionately difficult | AC25: Up to INR 50 crore | AD25: 7 | AE25: Testing confirms the service is fully usable when every non-essential consent is declined, refusal is as easy as acceptance, and the necessary/optional split is documented.
A26: CON-03 | B26: CON | C26: Consent | D26: Consent request in clear and plain language with contact details | E26: High | F26: =IF(E26="Critical",4,IF(E26="High",3,IF(E26="Medium",2,1))) | G26: 1.1 | H26: Yes | I26: in scope | J26: s.6(3), DPDP Act, 2023 | K26: [Rules citation to be verified] | L26: VERIFY_AGAINST_NOTIFIED_RULES | M26: 3 | N26: =IF(OR(H26="No",M26="",UPPER(M26)="NA"),0,1) | O26: =IF(H26="No","Out of scope",IF(UPPER(M26)="NA","Not applicable",IF(M26="","Not assessed",IF(M26>=4,"Compliant",IF(M26>=3,"Substantially compliant",IF(M26>=2,"Partially compliant","Non-compliant")))))) | P26: =IF(N26=0,"",F26*(4-M26)) | Q26: =IF(P26="","",IF(P26>=12,"Critical",IF(P26>=8,"High",IF(P26>=4,"Medium",IF(P26>=1,"Low","None"))))) | R26: =IF(AND(N26=1,M26<3),1,0) | S26: =IF(N26=0,"",M26*G26) | T26: =IF(N26=0,"",4*G26) | U26: The consent request is short and in plain language and names the entity. It does not provide the contact details of the person able to answer questions about the processing, and directs the reader to a 47-page combined policy document for detail. | V26: WP-042 | W26: Meera Raghunathan, Head of Legal & Compliance | Y26: Every request for consent must be presented in clear and plain language, giving the option to access it in English or an Eighth Schedule language, and must provide the contact details of the Data Protection Officer or other person authorised to respond on the Data Fiduciary's behalf. | Z26: Is the consent request written in plain language accessible to a general audience, and does it carry the required contact details at the point of request rather than only deep in a policy? | AA26: Inspect consent text for readability and for contact details; assess against a plain-language standard. | AB26: Consent request text with contact details present at the point of request · Readability assessment or plain-language review record · Language options available at the point of request | AC26: Up to INR 50 crore | AD26: 7 | AE26: Consent text is demonstrably plain, reviewed against a readability standard, carries contact details in-line, and offers language options at the point of request.
A27: CON-04 | B27: CON | C27: Consent | D27: Withdrawal of consent as easy as giving it | E27: Critical | F27: =IF(E27="Critical",4,IF(E27="High",3,IF(E27="Medium",2,1))) | G27: 1.3 | H27: Yes | I27: in scope | J27: s.6(4), DPDP Act, 2023 | K27: — | L27: — | M27: 1 | N27: =IF(OR(H27="No",M27="",UPPER(M27)="NA"),0,1) | O27: =IF(H27="No","Out of scope",IF(UPPER(M27)="NA","Not applicable",IF(M27="","Not assessed",IF(M27>=4,"Compliant",IF(M27>=3,"Substantially compliant",IF(M27>=2,"Partially compliant","Non-compliant")))))) | P27: =IF(N27=0,"",F27*(4-M27)) | Q27: =IF(P27="","",IF(P27>=12,"Critical",IF(P27>=8,"High",IF(P27>=4,"Medium",IF(P27>=1,"Low","None"))))) | R27: =IF(AND(N27=1,M27<3),1,0) | S27: =IF(N27=0,"",M27*G27) | T27: =IF(N27=0,"",4*G27) | U27: Withdrawal of consent is not available in the application. Marketing preferences can be toggled, but withdrawal of consent for processing requires an email to the support address, after which an agent follows a manual runbook. Against a two-tap consent action this is plainly not as easy to withdraw as to give. | V27: WP-043 | W27: Rohit Menon, Head of Product | Y27: The Data Principal has the right to withdraw consent at any time, and the ease of doing so must be comparable to the ease with which consent was given. | Z27: Can consent be withdrawn through the same channel and with comparable effort to giving it — a self-service control where consent was given in-app — or does withdrawal require an email, a call, or navigating to an obscure setting? | AA27: Re-performance: withdraw consent through each available route, counting steps and elapsed time, and compare against the steps to give it. | AB27: Self-service withdrawal control on the same surface as collection · Step-count comparison between giving and withdrawing · Evidence of withdrawals actually processed end to end | AC27: Up to INR 50 crore | AD27: 7 | AE27: Withdrawal is available on the same surface with comparable effort, tested end to end, and the step-count comparison is documented.
A28: CON-05 | B28: CON | C28: Consent | D28: Consequences of withdrawal disclosed and borne by the Data Principal | E28: Medium | F28: =IF(E28="Critical",4,IF(E28="High",3,IF(E28="Medium",2,1))) | G28: 1 | H28: Yes | I28: in scope | J28: s.6(5), s.6(6), DPDP Act, 2023 | K28: — | L28: — | M28: 2 | N28: =IF(OR(H28="No",M28="",UPPER(M28)="NA"),0,1) | O28: =IF(H28="No","Out of scope",IF(UPPER(M28)="NA","Not applicable",IF(M28="","Not assessed",IF(M28>=4,"Compliant",IF(M28>=3,"Substantially compliant",IF(M28>=2,"Partially compliant","Non-compliant")))))) | P28: =IF(N28=0,"",F28*(4-M28)) | Q28: =IF(P28="","",IF(P28>=12,"Critical",IF(P28>=8,"High",IF(P28>=4,"Medium",IF(P28>=1,"Low","None"))))) | R28: =IF(AND(N28=1,M28<3),1,0) | S28: =IF(N28=0,"",M28*G28) | T28: =IF(N28=0,"",4*G28) | U28: Consequences of withdrawal are described in the policy document but are not surfaced at the point of withdrawal, and the description does not distinguish consequences that follow from the withdrawal itself from service changes the entity elects to make. | V28: WP-044 | W28: Meera Raghunathan, Head of Legal & Compliance | Y28: The Data Principal bears the consequences of withdrawal of consent, and those consequences must be made known. Withdrawal does not affect the legality of processing carried out before it. | Z28: Are the consequences of withdrawal explained accurately at the point of withdrawal — neither understated nor exaggerated into a deterrent? | AA28: Inspect withdrawal interface text; assess whether stated consequences are accurate and proportionate rather than discouraging. | AB28: Withdrawal interface text describing actual consequences · Verification that stated consequences match what technically follows · Absence of deterrent framing or exaggerated warnings | AC28: Up to INR 50 crore | AD28: 7 | AE28: Consequences are accurately and neutrally stated, verified against what technically occurs, and free of deterrent framing.
A29: CON-06 | B29: CON | C29: Consent | D29: Processing ceases within a reasonable time of withdrawal | E29: Critical | F29: =IF(E29="Critical",4,IF(E29="High",3,IF(E29="Medium",2,1))) | G29: 1.3 | H29: Yes | I29: in scope | J29: s.6(6), DPDP Act, 2023 | K29: — | L29: — | M29: 1 | N29: =IF(OR(H29="No",M29="",UPPER(M29)="NA"),0,1) | O29: =IF(H29="No","Out of scope",IF(UPPER(M29)="NA","Not applicable",IF(M29="","Not assessed",IF(M29>=4,"Compliant",IF(M29>=3,"Substantially compliant",IF(M29>=2,"Partially compliant","Non-compliant")))))) | P29: =IF(N29=0,"",F29*(4-M29)) | Q29: =IF(P29="","",IF(P29>=12,"Critical",IF(P29>=8,"High",IF(P29>=4,"Medium",IF(P29>=1,"Low","None"))))) | R29: =IF(AND(N29=1,M29<3),1,0) | S29: =IF(N29=0,"",M29*G29) | T29: =IF(N29=0,"",4*G29) | U29: Testing of three withdrawal requests found processing continued after withdrawal in all three. Marketing suppression was applied within 48 hours, but the Snowflake warehouse, the CleverTap audience and the churn model training set retained and continued to use the records. Median elapsed time to full cessation could not be established because the entity does not measure it. | V29: WP-045 | W29: Devika Iyer, VP Engineering | Y29: On withdrawal of consent, the Data Fiduciary must, within a reasonable time, cease processing the personal data unless such processing without consent is required or authorised by law, and must cause its Data Processors to cease as well. | Z29: How long after withdrawal does processing actually stop, across all systems including analytics, marketing platforms, warehouses and processors — and is that interval measured rather than assumed? | AA29: Re-performance: withdraw consent for a test record and trace it across every downstream system, measuring elapsed time to cessation in each. | AB29: Measured cessation times across primary, secondary and vendor systems · Propagation mechanism from the consent store to downstream consumers · Exception log for systems where cessation is delayed or manual | AC29: Up to INR 50 crore | AD29: 7 | AE29: Withdrawal propagates to every consumer including processors within a measured and documented interval, exceptions are logged and owned, and tracing a test record confirms end-to-end cessation.
A30: CON-07 | B30: CON | C30: Consent | D30: Consent artefacts retained and provable | E30: Critical | F30: =IF(E30="Critical",4,IF(E30="High",3,IF(E30="Medium",2,1))) | G30: 1.4 | H30: Yes | I30: in scope | J30: s.6(10), DPDP Act, 2023 | K30: — | L30: — | M30: 1 | N30: =IF(OR(H30="No",M30="",UPPER(M30)="NA"),0,1) | O30: =IF(H30="No","Out of scope",IF(UPPER(M30)="NA","Not applicable",IF(M30="","Not assessed",IF(M30>=4,"Compliant",IF(M30>=3,"Substantially compliant",IF(M30>=2,"Partially compliant","Non-compliant")))))) | P30: =IF(N30=0,"",F30*(4-M30)) | Q30: =IF(P30="","",IF(P30>=12,"Critical",IF(P30>=8,"High",IF(P30>=4,"Medium",IF(P30>=1,"Low","None"))))) | R30: =IF(AND(N30=1,M30<3),1,0) | S30: =IF(N30=0,"",M30*G30) | T30: =IF(N30=0,"",4*G30) | U30: The consent table records a current state per Data Principal with a single last-updated timestamp. It does not retain the notice version, the interface, the purposes in force at the time, or any history of change. For two of five sampled Data Principals the entity could not demonstrate what was consented to or when. The Act places the burden of proving valid consent on the Data Fiduciary and that burden could not presently be discharged. | V30: WP-046 | W30: Devika Iyer, VP Engineering | Y30: Where a question arises as to whether notice was given and consent obtained in accordance with the Act, the Data Fiduciary bears the burden of proving it. | Z30: For a given Data Principal, can the entity produce a tamper-evident record of what was consented to, when, through what interface, and against which version of the notice? | AA30: Re-performance: select three Data Principals at random and require production of the full consent artefact including notice version and interface reference. | AB30: Consent records capturing timestamp, purpose set, interface, notice version · Tamper-evidence or immutability controls over the consent store · Successful retrieval for randomly selected individuals | AC30: Up to INR 50 crore | AD30: 7 | AE30: Complete, tamper-evident artefacts capture purpose set, timestamp, interface and notice version, are retrievable on demand for any individual, and testing confirms retrieval.
... A33: CMG-02 | B33: CMG | C33: Consent Manager | D33: Consent Manager interface integrity and record reconciliation | E33: High | F33: =IF(E33="Critical",4,IF(E33="High",3,IF(E33="Medium",2,1))) | G33: 1.1 | H33: Yes | I33: in scope | J33: s.6(7), s.6(10), s.8(1), DPDP Act, 2023 | K33: [Rules citation to be verified] | L33: VERIFY_AGAINST_NOTIFIED_RULES | M33: 2 | N33: =IF(OR(H33="No",M33="",UPPER(M33)="NA"),0,1) | O33: =IF(H33="No","Out of scope",IF(UPPER(M33)="NA","Not applicable",IF(M33="","Not assessed",IF(M33>=4,"Compliant",IF(M33>=3,"Substantially compliant",IF(M33>=2,"Partially compliant","Non-compliant")))))) | P33: =IF(N33=0,"",F33*(4-M33)) | Q33: =IF(P33="","",IF(P33>=12,"Critical",IF(P33>=8,"High",IF(P33>=4,"Medium",IF(P33>=1,"Low","None"))))) | R33: =IF(AND(N33=1,M33<3),1,0) | S33: =IF(N33=0,"",M33*G33) | T33: =IF(N33=0,"",4*G33) | U33: Consent artefacts received through the aggregator are stored and the data fetch is scoped to the artefact. Reconciliation between artefacts held by the aggregator and consents recorded internally is not performed, so a revoked artefact would not necessarily stop an internal reuse of previously fetched financial information. | V33: WP-051 | W33: Devika Iyer, VP Engineering | Y33: Reliance on a Consent Manager does not displace the Data Fiduciary's own accountability under section 8(1) or its burden of proof under section 6(10). | Z33: Are consent records received from the Consent Manager reconciled against the entity's own processing, so that a withdrawal registered with the intermediary reliably reaches and halts the entity's systems? | AA33: Re-performance: register a withdrawal through the Consent Manager and trace propagation into the entity's systems; inspect reconciliation controls and exception handling. | AB33: Integration design and reconciliation controls between the intermediary and internal consent state · Exception reports for failed or delayed synchronisation · End-to-end test evidence for a withdrawal originating at the intermediary | AC33: Up to INR 50 crore | AD33: 7 | AE33: Automated reconciliation with exception alerting is in place, withdrawal propagation is tested end to end, and the entity retains its own provable consent state.
A34: CMG-03 | B34: CMG | C34: Consent Manager | D34: Own registration and obligations where acting as a Consent Manager | E34: Critical | F34: =IF(E34="Critical",4,IF(E34="High",3,IF(E34="Medium",2,1))) | G34: 1.2 | H34: No | I34: requires is_consent_manager | J34: s.6(8), s.6(9), DPDP Act, 2023 | K34: [Rules citation to be verified] | L34: VERIFY_AGAINST_NOTIFIED_RULES | N34: =IF(OR(H34="No",M34="",UPPER(M34)="NA"),0,1) | O34: =IF(H34="No","Out of scope",IF(UPPER(M34)="NA","Not applicable",IF(M34="","Not assessed",IF(M34>=4,"Compliant",IF(M34>=3,"Substantially compliant",IF(M34>=2,"Partially compliant","Non-compliant")))))) | P34: =IF(N34=0,"",F34*(4-M34)) | Q34: =IF(P34="","",IF(P34>=12,"Critical",IF(P34>=8,"High",IF(P34>=4,"Medium",IF(P34>=1,"Low","None"))))) | R34: =IF(AND(N34=1,M34<3),1,0) | S34: =IF(N34=0,"",M34*G34) | T34: =IF(N34=0,"",4*G34) | Y34: An entity acting as a Consent Manager must be registered with the Board, subject to prescribed conditions, and must discharge the obligations of that role including accountability to the Data Principal. | Z34: If the entity itself acts as a Consent Manager, is it registered, does it meet the prescribed conditions on a continuing basis, and can it evidence accountability to Data Principals rather than to the Data Fiduciaries paying it? | AA34: Inspect registration, continuing compliance with prescribed conditions, and the operational independence of the Data Principal-facing function. | AB34: Certificate or evidence of registration with the Board · Continuing compliance monitoring against the prescribed conditions · Governance evidencing accountability to Data Principals, including conflict management | AC34: Up to INR 50 crore | AD34: 7 | AE34: Registered, with continuing compliance actively monitored, and demonstrable governance — including conflict-of-interest management — establishing accountability to Data Principals.
A35: LGU-01 | B35: LGU | C35: Legitimate Uses | D35: Legitimate use relied upon is a specific statutory limb | E35: Critical | F35: =IF(E35="Critical",4,IF(E35="High",3,IF(E35="Medium",2,1))) | G35: 1.3 | H35: Yes | I35: in scope | J35: s.7, DPDP Act, 2023 | K35: — | L35: — | M35: 2 | N35: =IF(OR(H35="No",M35="",UPPER(M35)="NA"),0,1) | O35: =IF(H35="No","Out of scope",IF(UPPER(M35)="NA","Not applicable",IF(M35="","Not assessed",IF(M35>=4,"Compliant",IF(M35>=3,"Substantially compliant",IF(M35>=2,"Partially compliant","Non-compliant")))))) | P35: =IF(N35=0,"",F35*(4-M35)) | Q35: =IF(P35="","",IF(P35>=12,"Critical",IF(P35>=8,"High",IF(P35>=4,"Medium",IF(P35>=1,"Low","None"))))) | R35: =IF(AND(N35=1,M35<3),1,0) | S35: =IF(N35=0,"",M35*G35) | T35: =IF(N35=0,"",4*G35) | U35: Where consent is not relied upon, the entity's documentation cites 'legitimate use' generically rather than identifying the specific statutory limb. Two activities — fraud analytics using device signals, and the credit bureau reporting of repayment behaviour — rest on limbs that do not on their terms extend to that processing. | V35: WP-055 | W35: Meera Raghunathan, Head of Legal & Compliance | Y35: Processing without consent is permitted only for the certain legitimate uses enumerated in section 7. The list is closed; there is no general balancing or legitimate-interests ground. | Z35: For every activity proceeding without consent, is the specific section 7 limb identified and defensible — and has the entity avoided importing a legitimate-interests analysis from another regime? | AA35: Inspect the basis register; re-perform the analysis for each legitimate use relied upon, testing the fit against the statutory wording. | AB35: Identification of the specific limb, by sub-clause, for each activity · Written analysis of why the activity falls within it · Absence of reliance on a general balancing test | AC35: Up to INR 50 crore | AD35: 7 | AE35: Each reliance cites a specific sub-clause with a documented, defensible analysis, reviewed by legal, and reliance is narrowly confined to what the limb actually authorises.
A36: LGU-02 | B36: LGU | C36: Legitimate Uses | D36: Employment-purposes limb correctly scoped | E36: High | F36: =IF(E36="Critical",4,IF(E36="High",3,IF(E36="Medium",2,1))) | G36: 1.2 | H36: Yes | I36: in scope | J36: s.7(i), DPDP Act, 2023 | K36: — | L36: — | M36: 3 | N36: =IF(OR(H36="No",M36="",UPPER(M36)="NA"),0,1) | O36: =IF(H36="No","Out of scope",IF(UPPER(M36)="NA","Not applicable",IF(M36="","Not assessed",IF(M36>=4,"Compliant",IF(M36>=3,"Substantially compliant",IF(M36>=2,"Partially compliant","Non-compliant")))))) | P36: =IF(N36=0,"",F36*(4-M36)) | Q36: =IF(P36="","",IF(P36>=12,"Critical",IF(P36>=8,"High",IF(P36>=4,"Medium",IF(P36>=1,"Low","None"))))) | R36: =IF(AND(N36=1,M36<3),1,0) | S36: =IF(N36=0,"",M36*G36) | T36: =IF(N36=0,"",4*G36) | U36: Employment-purpose processing is documented for payroll, benefits and performance. The collections team's screen and keystroke monitoring is also placed under this limb; the connection to safeguarding the employer from loss or to provision of a service to the employee is asserted rather than evidenced, and employees have not been informed of the monitoring. | V36: WP-056 | W36: Sneha Kulkarni, Head of People | Y36: Processing is a legitimate use where it is necessary for purposes of employment, or those related to safeguarding the employer from loss or liability, such as prevention of corporate espionage, maintenance of confidentiality of trade secrets or intellectual property, or provision of any service or benefit sought by an employee. | Z36: Where employee data is processed under section 7(i), is each use necessary for employment or for safeguarding against loss or liability — and does the entity avoid treating the limb as blanket authority for all employee monitoring? | AA36: Inspect employee data processing inventory; test each monitoring or analytics use against the necessity standard in the limb. | AB36: Inventory of employee data processing with the limb mapped per use · Necessity analysis for monitoring, productivity analytics and surveillance · Employee-facing transparency documentation | AC36: Up to INR 50 crore | AD36: 7 | AE36: Each use is mapped to the limb with a documented necessity analysis, intrusive monitoring is separately justified and proportionate, and employees are informed.
A37: LGU-03 | B37: LGU | C37: Legitimate Uses | D37: Voluntary provision limb not over-extended | E37: Medium | F37: =IF(E37="Critical",4,IF(E37="High",3,IF(E37="Medium",2,1))) | G37: 1 | H37: Yes | I37: in scope | J37: s.7(a), DPDP Act, 2023 | K37: — | L37: — | M37: 3 | N37: =IF(OR(H37="No",M37="",UPPER(M37)="NA"),0,1) | O37: =IF(H37="No","Out of scope",IF(UPPER(M37)="NA","Not applicable",IF(M37="","Not assessed",IF(M37>=4,"Compliant",IF(M37>=3,"Substantially compliant",IF(M37>=2,"Partially compliant","Non-compliant")))))) | P37: =IF(N37=0,"",F37*(4-M37)) | Q37: =IF(P37="","",IF(P37>=12,"Critical",IF(P37>=8,"High",IF(P37>=4,"Medium",IF(P37>=1,"Low","None"))))) | R37: =IF(AND(N37=1,M37<3),1,0) | S37: =IF(N37=0,"",M37*G37) | T37: =IF(N37=0,"",4*G37) | U37: Voluntary provision is relied upon for support interactions initiated by the Data Principal, which is appropriate. The same limb is stretched to cover retention of call recordings for model training, which is a different purpose from the one for which the data was voluntarily provided. | V37: WP-057 | W37: Anita Desai, Head of Customer Experience | Y37: Processing is a legitimate use where the Data Principal has voluntarily provided personal data for a specified purpose and has not indicated objection, but only for that purpose. | Z37: Where the voluntary-provision limb is relied upon, is processing confined to the specific purpose for which the data was volunteered, and is there a working mechanism for the Data Principal to object? | AA37: Inspect the activities relying on this limb; test whether processing extends beyond the volunteered purpose and whether objection is operable. | AB37: Identification of the purpose for which data was volunteered, per activity · Controls confining processing to that purpose · Operable objection mechanism with evidence of objections honoured | AC37: Up to INR 50 crore | AD37: 7 | AE37: Processing is technically and procedurally confined to the volunteered purpose, an operable objection mechanism exists, and objections are evidenced as honoured.
A38: RET-01 | B38: RET | C38: Retention & Erasure | D38: Retention schedule defined per data category and purpose | E38: High | F38: =IF(E38="Critical",4,IF(E38="High",3,IF(E38="Medium",2,1))) | G38: 1.2 | H38: Yes | I38: in scope | J38: s.8(7), DPDP Act, 2023 | K38: [Rules citation to be verified] | L38: VERIFY_AGAINST_NOTIFIED_RULES | M38: 2 | N38: =IF(OR(H38="No",M38="",UPPER(M38)="NA"),0,1) | O38: =IF(H38="No","Out of scope",IF(UPPER(M38)="NA","Not applicable",IF(M38="","Not assessed",IF(M38>=4,"Compliant",IF(M38>=3,"Substantially compliant",IF(M38>=2,"Partially compliant","Non-compliant")))))) | P38: =IF(N38=0,"",F38*(4-M38)) | Q38: =IF(P38="","",IF(P38>=12,"Critical",IF(P38>=8,"High",IF(P38>=4,"Medium",IF(P38>=1,"Low","None"))))) | R38: =IF(AND(N38=1,M38<3),1,0) | S38: =IF(N38=0,"",M38*G38) | T38: =IF(N38=0,"",4*G38) | U38: A retention schedule exists but is expressed at system level rather than by data category and purpose, and defaults to 'as required by applicable law' for 11 of 19 systems. Snowflake and the S3 data lake have no defined retention period at all; the oldest personal data located during testing dated from 2019. | V38: WP-060 | W38: Devika Iyer, VP Engineering | Y38: Personal data must be erased on withdrawal of consent or as soon as it is reasonable to assume the specified purpose is no longer being served, whichever is earlier, unless retention is necessary for compliance with law. | Z38: Is there a retention schedule stating, per data category and purpose, how long data is kept and on what legal footing — with retention beyond purpose justified by a specific legal requirement rather than by general prudence? | AA38: Inspect the retention schedule against the processing register; test the stated legal basis for each retention period exceeding the purpose. | AB38: Retention schedule mapped to data categories and purposes · Specific statutory or regulatory citation for each extended retention period · Approval and periodic review records | AC38: Up to INR 50 crore | AD38: 7 | AE38: A complete schedule covers every category and purpose, each extended period cites the specific legal requirement, and the schedule is reviewed and approved on a defined cycle.
A39: RET-02 | B39: RET | C39: Retention & Erasure | D39: Erasure on withdrawal of consent or purpose completion | E39: Critical | F39: =IF(E39="Critical",4,IF(E39="High",3,IF(E39="Medium",2,1))) | G39: 1.3 | H39: Yes | I39: in scope | J39: s.8(7), DPDP Act, 2023 | K39: [Rules citation to be verified] | L39: VERIFY_AGAINST_NOTIFIED_RULES | M39: 1 | N39: =IF(OR(H39="No",M39="",UPPER(M39)="NA"),0,1) | O39: =IF(H39="No","Out of scope",IF(UPPER(M39)="NA","Not applicable",IF(M39="","Not assessed",IF(M39>=4,"Compliant",IF(M39>=3,"Substantially compliant",IF(M39>=2,"Partially compliant","Non-compliant")))))) | P39: =IF(N39=0,"",F39*(4-M39)) | Q39: =IF(P39="","",IF(P39>=12,"Critical",IF(P39>=8,"High",IF(P39>=4,"Medium",IF(P39>=1,"Low","None"))))) | R39: =IF(AND(N39=1,M39<3),1,0) | S39: =IF(N39=0,"",M39*G39) | T39: =IF(N39=0,"",4*G39) | U39: Erasure on withdrawal or purpose completion is not implemented. The manual runbook noted at CON-04 anonymises the CRM record but leaves the warehouse, the ledger, the communications platforms and the backups untouched. RBI and PMLA retention requirements were cited as justification but have not been mapped to data categories, so they operate as a blanket exception rather than a bounded one. | V39: WP-061 | W39: Devika Iyer, VP Engineering | Y39: On withdrawal of consent or once the purpose is no longer being served, the Data Fiduciary must erase the personal data, unless retention is necessary for compliance with any law. | Z39: Is erasure actually triggered and completed on withdrawal or purpose completion — and is it erasure, as distinct from a soft-delete flag that leaves the record fully intact and queryable? | AA39: Re-performance: withdraw consent for a test record, then query every store directly to confirm the data is gone rather than flagged. | AB39: Automated erasure triggers tied to withdrawal and purpose-completion events · Evidence from direct queries that data is removed, not merely flagged · Erasure logs recording what was erased and when | AC39: Up to INR 50 crore | AD39: 7 | AE39: Erasure is automatically triggered, verified by direct query across stores, logged, and exceptions where law requires retention are individually documented.
A40: RET-03 | B40: RET | C40: Retention & Erasure | D40: Erasure propagated to processors, backups and derived stores | E40: Critical | F40: =IF(E40="Critical",4,IF(E40="High",3,IF(E40="Medium",2,1))) | G40: 1.3 | H40: Yes | I40: in scope | J40: s.8(7), DPDP Act, 2023 | K40: [Rules citation to be verified] | L40: VERIFY_AGAINST_NOTIFIED_RULES | M40: 1 | N40: =IF(OR(H40="No",M40="",UPPER(M40)="NA"),0,1) | O40: =IF(H40="No","Out of scope",IF(UPPER(M40)="NA","Not applicable",IF(M40="","Not assessed",IF(M40>=4,"Compliant",IF(M40>=3,"Substantially compliant",IF(M40>=2,"Partially compliant","Non-compliant")))))) | P40: =IF(N40=0,"",F40*(4-M40)) | Q40: =IF(P40="","",IF(P40>=12,"Critical",IF(P40>=8,"High",IF(P40>=4,"Medium",IF(P40>=1,"Low","None"))))) | R40: =IF(AND(N40=1,M40<3),1,0) | S40: =IF(N40=0,"",M40*G40) | T40: =IF(N40=0,"",4*G40) | U40: Erasure does not propagate. Testing confirmed that a record erased in Kavach CRM remained present in Snowflake, in the dbt derived tables, in CleverTap and in Gupshup's message logs. No processor has been issued an erasure instruction in the period, and the vendor contracts contain no mechanism for doing so. | V40: WP-062 | W40: Devika Iyer, VP Engineering | Y40: The Data Fiduciary must cause its Data Processors to erase personal data that was made available to them for processing. | Z40: Does erasure reach processors, data warehouses, analytics environments, search indices, caches, logs and backups — and is completion confirmed rather than assumed? | AA40: Trace an erasure request across the full data topology; inspect processor erasure confirmations; test the treatment of backups and derived datasets. | AB40: Data topology map identifying every store holding personal data · Processor erasure instructions and written confirmations of completion · Documented approach to backups, including erasure on restore | AC40: Up to INR 50 crore | AD40: 7 | AE40: A complete topology drives erasure across every store, processors return confirmations that are tracked, and the backup approach is documented including re-erasure on restore.
A41: RET-04 | B41: RET | C41: Retention & Erasure | D41: Deemed purpose completion on Data Principal inactivity | E41: High | F41: =IF(E41="Critical",4,IF(E41="High",3,IF(E41="Medium",2,1))) | G41: 1.1 | H41: Yes | I41: in scope | J41: s.8(10), DPDP Act, 2023 | K41: [Rules citation to be verified] | L41: VERIFY_AGAINST_NOTIFIED_RULES | M41: 0 | N41: =IF(OR(H41="No",M41="",UPPER(M41)="NA"),0,1) | O41: =IF(H41="No","Out of scope",IF(UPPER(M41)="NA","Not applicable",IF(M41="","Not assessed",IF(M41>=4,"Compliant",IF(M41>=3,"Substantially compliant",IF(M41>=2,"Partially compliant","Non-compliant")))))) | P41: =IF(N41=0,"",F41*(4-M41)) | Q41: =IF(P41="","",IF(P41>=12,"Critical",IF(P41>=8,"High",IF(P41>=4,"Medium",IF(P41>=1,"Low","None"))))) | R41: =IF(AND(N41=1,M41<3),1,0) | S41: =IF(N41=0,"",M41*G41) | T41: =IF(N41=0,"",4*G41) | U41: There is no concept of deemed purpose completion on inactivity. Accounts dormant since 2019 remain fully populated and continue to be included in marketing audiences. Approximately 2.1 million Data Principals have had no interaction with the platform for over three years. | V41: WP-063 | W41: Devika Iyer, VP Engineering | Y41: The purpose is deemed no longer to be served if the Data Principal neither approaches the Data Fiduciary for the performance of the purpose nor exercises any of their rights in relation to it, for such period as may be prescribed. | Z41: Does the entity track Data Principal inactivity and treat the prescribed period of inactivity as triggering erasure — and does it know whether it falls within a class for which specific periods are prescribed? | AA41: Inspect inactivity tracking and the erasure trigger; test the class determination against the prescribed thresholds; sample dormant records for erasure. | AB41: Inactivity definition and tracking mechanism per data category · Class determination assessment against the prescribed thresholds · Erasure records for dormant populations | AC41: Up to INR 50 crore | AD41: 7 | AE41: Inactivity is tracked per category, the class determination is documented, erasure triggers operate on the prescribed period, and dormant-population erasure is evidenced.
A42: RET-05 | B42: RET | C42: Retention & Erasure | D42: Advance notice before erasure where required | E42: Medium | F42: =IF(E42="Critical",4,IF(E42="High",3,IF(E42="Medium",2,1))) | G42: 0.9 | H42: Yes | I42: in scope | J42: s.8(7), s.8(10) read with the Rules, DPDP Act, 2023 | K42: [Rules citation to be verified] | L42: VERIFY_AGAINST_NOTIFIED_RULES | M42: 0 | N42: =IF(OR(H42="No",M42="",UPPER(M42)="NA"),0,1) | O42: =IF(H42="No","Out of scope",IF(UPPER(M42)="NA","Not applicable",IF(M42="","Not assessed",IF(M42>=4,"Compliant",IF(M42>=3,"Substantially compliant",IF(M42>=2,"Partially compliant","Non-compliant")))))) | P42: =IF(N42=0,"",F42*(4-M42)) | Q42: =IF(P42="","",IF(P42>=12,"Critical",IF(P42>=8,"High",IF(P42>=4,"Medium",IF(P42>=1,"Low","None"))))) | R42: =IF(AND(N42=1,M42<3),1,0) | S42: =IF(N42=0,"",M42*G42) | T42: =IF(N42=0,"",4*G42) | U42: No advance intimation is given before erasure, because no scheduled erasure takes place. The requirement has not been designed for. | V42: WP-064 | W42: Devika Iyer, VP Engineering | Y42: The Rules are understood to require advance intimation to the Data Principal before erasure on the expiry of a prescribed retention period, so that the individual may act to preserve access if they wish. | Z42: Where a prescribed retention period is about to expire, is advance notice given to the Data Principal in the prescribed manner and within the prescribed period before erasure? | AA42: Inspect the pre-erasure notification mechanism and despatch logs; test that timing precedes erasure by the required interval. | AB42: Pre-erasure notification template and trigger configuration · Despatch logs showing notice preceding erasure by the required interval · Handling of Data Principal responses to such notices | AC42: Up to INR 50 crore | AD42: 7 | AE42: Pre-erasure notification is automated on the prescribed interval, despatch is logged, and responses are handled through a defined process.
A43: RGT-01 | B43: RGT | C43: Data Principal Rights | D43: Right to access information about personal data | E43: High | F43: =IF(E43="Critical",4,IF(E43="High",3,IF(E43="Medium",2,1))) | G43: 1.2 | H43: Yes | I43: in scope | J43: s.11(1), DPDP Act, 2023 | K43: [Rules citation to be verified] | L43: VERIFY_AGAINST_NOTIFIED_RULES | M43: 2 | N43: =IF(OR(H43="No",M43="",UPPER(M43)="NA"),0,1) | O43: =IF(H43="No","Out of scope",IF(UPPER(M43)="NA","Not applicable",IF(M43="","Not assessed",IF(M43>=4,"Compliant",IF(M43>=3,"Substantially compliant",IF(M43>=2,"Partially compliant","Non-compliant")))))) | P43: =IF(N43=0,"",F43*(4-M43)) | Q43: =IF(P43="","",IF(P43>=12,"Critical",IF(P43>=8,"High",IF(P43>=4,"Medium",IF(P43>=1,"Low","None"))))) | R43: =IF(AND(N43=1,M43<3),1,0) | S43: =IF(N43=0,"",M43*G43) | T43: =IF(N43=0,"",4*G43) | U43: An access request route exists via the grievance form and produces a summary of profile data. It does not include the identities of processors or other recipients with whom data has been shared, nor a description of the processing activities. Two of the four requests received in the period were answered outside 30 days. | V43: WP-070 | W43: Anita Desai, Head of Customer Experience | Y43: A Data Principal who has previously given consent is entitled, on request, to a summary of the personal data being processed and the processing activities undertaken, the identities of all other Data Fiduciaries and Data Processors with whom the personal data has been shared together with a description of the data shared, and any other prescribed information. | Z43: Can the entity produce, on request, a summary of the data held, the processing activities, and the identities of every recipient with a description of what was shared? The recipient-identity element is the part most commonly absent. | AA43: Re-performance: submit an access request as a Data Principal and evaluate the completeness of the response against the statutory requirements. | AB43: Access request procedure and fulfilment records · Sample response demonstrating all three statutory elements · Mechanism for compiling recipient identities and data shared | AC43: Up to INR 50 crore | AD43: 7 | AE43: Testing confirms responses cover all statutory elements including full recipient identities and descriptions of data shared, produced within the prescribed period through a repeatable process.
A44: RGT-02 | B44: RGT | C44: Data Principal Rights | D44: Right to correction, completion and updating | E44: High | F44: =IF(E44="Critical",4,IF(E44="High",3,IF(E44="Medium",2,1))) | G44: 1.1 | H44: Yes | I44: in scope | J44: s.12(1), s.12(2), DPDP Act, 2023 | K44: [Rules citation to be verified] | L44: VERIFY_AGAINST_NOTIFIED_RULES | M44: 3 | N44: =IF(OR(H44="No",M44="",UPPER(M44)="NA"),0,1) | O44: =IF(H44="No","Out of scope",IF(UPPER(M44)="NA","Not applicable",IF(M44="","Not assessed",IF(M44>=4,"Compliant",IF(M44>=3,"Substantially compliant",IF(M44>=2,"Partially compliant","Non-compliant")))))) | P44: =IF(N44=0,"",F44*(4-M44)) | Q44: =IF(P44="","",IF(P44>=12,"Critical",IF(P44>=8,"High",IF(P44>=4,"Medium",IF(P44>=1,"Low","None"))))) | R44: =IF(AND(N44=1,M44<3),1,0) | S44: =IF(N44=0,"",M44*G44) | T44: =IF(N44=0,"",4*G44) | U44: Correction and updating of profile data is self-service in the application and works as described. Completion of incomplete records and correction of data held only in the warehouse or with processors requires a manual request and is not propagated, as noted at PUR-04. | V44: WP-071 | W44: Devika Iyer, VP Engineering | Y44: A Data Principal has the right to correction, completion and updating of personal data. On receiving such a request the Data Fiduciary must correct inaccurate or misleading data, complete incomplete data, and update it. | Z44: Can a Data Principal have data corrected, completed and updated, and do those corrections propagate to processors and to other Data Fiduciaries with whom the data was shared? | AA44: Re-performance: submit a correction request and trace propagation to downstream systems and third-party recipients. | AB44: Correction procedure and fulfilment records with elapsed times · Evidence of propagation to processors and onward recipients · Self-service correction capability where practicable | AC44: Up to INR 50 crore | AD44: 7 | AE44: Corrections are actioned within the prescribed period and demonstrably propagate to every downstream consumer and prior recipient, with self-service available where practicable.
A45: RGT-03 | B45: RGT | C45: Data Principal Rights | D45: Right to erasure on request | E45: High | F45: =IF(E45="Critical",4,IF(E45="High",3,IF(E45="Medium",2,1))) | G45: 1.2 | H45: Yes | I45: in scope | J45: s.12(3), DPDP Act, 2023 | K45: [Rules citation to be verified] | L45: VERIFY_AGAINST_NOTIFIED_RULES | M45: 1 | N45: =IF(OR(H45="No",M45="",UPPER(M45)="NA"),0,1) | O45: =IF(H45="No","Out of scope",IF(UPPER(M45)="NA","Not applicable",IF(M45="","Not assessed",IF(M45>=4,"Compliant",IF(M45>=3,"Substantially compliant",IF(M45>=2,"Partially compliant","Non-compliant")))))) | P45: =IF(N45=0,"",F45*(4-M45)) | Q45: =IF(P45="","",IF(P45>=12,"Critical",IF(P45>=8,"High",IF(P45>=4,"Medium",IF(P45>=1,"Low","None"))))) | R45: =IF(AND(N45=1,M45<3),1,0) | S45: =IF(N45=0,"",M45*G45) | T45: =IF(N45=0,"",4*G45) | U45: Erasure requests are accepted but cannot be fulfilled beyond the CRM, for the reasons at RET-03. Three of the three erasure requests received were closed as completed on the basis of CRM anonymisation alone, which overstates what was done and creates a misleading record. | V45: WP-072 | W45: Anita Desai, Head of Customer Experience | Y45: A Data Principal has the right to erasure of personal data, and on such a request the Data Fiduciary must erase unless retention is necessary for the specified purpose or for compliance with any law. | Z45: Is erasure on request actioned across all stores, with refusals confined to genuine legal retention requirements and explained to the Data Principal? | AA45: Re-performance: submit an erasure request and verify removal across stores; inspect the refusal log and test the justifications recorded. | AB45: Erasure request procedure and fulfilment records · Verification of removal across all identified stores · Refusal log with specific legal justification per refusal | AC45: Up to INR 50 crore | AD45: 7 | AE45: Erasure is actioned and verified across all stores within the prescribed period, and each refusal cites a specific legal basis and is communicated to the Data Principal.
A46: RGT-04 | B46: RGT | C46: Data Principal Rights | D46: Right to nominate | E46: Medium | F46: =IF(E46="Critical",4,IF(E46="High",3,IF(E46="Medium",2,1))) | G46: 0.9 | H46: Yes | I46: in scope | J46: s.14, DPDP Act, 2023 | K46: [Rules citation to be verified] | L46: VERIFY_AGAINST_NOTIFIED_RULES | M46: 0 | N46: =IF(OR(H46="No",M46="",UPPER(M46)="NA"),0,1) | O46: =IF(H46="No","Out of scope",IF(UPPER(M46)="NA","Not applicable",IF(M46="","Not assessed",IF(M46>=4,"Compliant",IF(M46>=3,"Substantially compliant",IF(M46>=2,"Partially compliant","Non-compliant")))))) | P46: =IF(N46=0,"",F46*(4-M46)) | Q46: =IF(P46="","",IF(P46>=12,"Critical",IF(P46>=8,"High",IF(P46>=4,"Medium",IF(P46>=1,"Low","None"))))) | R46: =IF(AND(N46=1,M46<3),1,0) | S46: =IF(N46=0,"",M46*G46) | T46: =IF(N46=0,"",4*G46) | U46: The right to nominate has not been implemented. There is no interface, no record structure and no operating procedure for giving effect to a nomination on death or incapacity. | V46: WP-073 | W46: Rohit Menon, Head of Product | Y46: A Data Principal has the right to nominate, in the prescribed manner, any other individual to exercise their rights under the Act in the event of the Data Principal's death or incapacity. | Z46: Is there a working mechanism for a Data Principal to nominate another individual, and a procedure for that nominee to be verified and to exercise rights when the trigger event occurs? | AA46: Inspect the nomination mechanism and the nominee verification procedure; test that nomination records are retrievable and actionable. | AB46: Nomination capture mechanism accessible to Data Principals · Nominee verification and rights-exercise procedure · Retrievable nomination records | AC46: Up to INR 50 crore | AD46: 7 | AE46: A structured nomination mechanism is available and publicised, records are retrievable, and a documented procedure governs nominee verification and rights exercise on death or incapacity.
... A51: GRV-03 | B51: GRV | C51: Grievance Redressal | D51: Grievance mechanism readily available and publicised | E51: Medium | F51: =IF(E51="Critical",4,IF(E51="High",3,IF(E51="Medium",2,1))) | G51: 1 | H51: Yes | I51: in scope | J51: s.13(1), s.13(3), DPDP Act, 2023 | K51: — | L51: — | M51: 3 | N51: =IF(OR(H51="No",M51="",UPPER(M51)="NA"),0,1) | O51: =IF(H51="No","Out of scope",IF(UPPER(M51)="NA","Not applicable",IF(M51="","Not assessed",IF(M51>=4,"Compliant",IF(M51>=3,"Substantially compliant",IF(M51>=2,"Partially compliant","Non-compliant")))))) | P51: =IF(N51=0,"",F51*(4-M51)) | Q51: =IF(P51="","",IF(P51>=12,"Critical",IF(P51>=8,"High",IF(P51>=4,"Medium",IF(P51>=1,"Low","None"))))) | R51: =IF(AND(N51=1,M51<3),1,0) | S51: =IF(N51=0,"",M51*G51) | T51: =IF(N51=0,"",4*G51) | U51: The grievance route is published in the app, on the website and in the privacy policy. It is not present in the Kavach Junior parent console and is not included in transactional communications, which is where a dissatisfied Data Principal is most likely to look. | V51: WP-082 | W51: Anita Desai, Head of Customer Experience | Y51: The means of grievance redressal must be readily available to the Data Principal, who must exhaust the opportunity so provided before approaching the Board. | Z51: Can a Data Principal find the grievance route without difficulty from any surface on which they interact with the entity, and is it published alongside the section 8(8) contact details? | AA51: Observation: attempt to locate the grievance route as a naive user from each surface, recording steps required. | AB51: Grievance route published on website, app, notice and communications · Step count to locate the route from each surface · Consistency of the route published across surfaces | AC51: Up to INR 50 crore | AD51: 7 | AE51: The route is prominently and consistently published on every surface, discoverable in a small number of steps, and aligned with the published contact details.
A52: GRV-04 | B52: GRV | C52: Grievance Redressal | D52: Grievance trend analysis feeding remediation | E52: Low | F52: =IF(E52="Critical",4,IF(E52="High",3,IF(E52="Medium",2,1))) | G52: 0.8 | H52: Yes | I52: in scope | J52: s.8(9), DPDP Act, 2023 | K52: — | L52: — | M52: 1 | N52: =IF(OR(H52="No",M52="",UPPER(M52)="NA"),0,1) | O52: =IF(H52="No","Out of scope",IF(UPPER(M52)="NA","Not applicable",IF(M52="","Not assessed",IF(M52>=4,"Compliant",IF(M52>=3,"Substantially compliant",IF(M52>=2,"Partially compliant","Non-compliant")))))) | P52: =IF(N52=0,"",F52*(4-M52)) | Q52: =IF(P52="","",IF(P52>=12,"Critical",IF(P52>=8,"High",IF(P52>=4,"Medium",IF(P52>=1,"Low","None"))))) | R52: =IF(AND(N52=1,M52<3),1,0) | S52: =IF(N52=0,"",M52*G52) | T52: =IF(N52=0,"",4*G52) | U52: No trend analysis is performed. Privacy grievances are not tagged, so the recurring theme identified during this assessment — inability to stop marketing contact after withdrawal — has never been reported to management as a pattern despite appearing in 9 of the 15 tickets sampled. | V52: WP-083 | W52: Anita Desai, Head of Customer Experience | Y52: An effective mechanism under section 8(9) implies more than case handling: the entity must be capable of identifying and addressing the systemic causes that generate grievances. | Z52: Are grievances categorised and analysed for root cause, with systemic issues escalated into the remediation plan rather than each case being closed in isolation? | AA52: Inspect grievance categorisation and trend reporting; test whether identified systemic issues resulted in a change. | AB52: Categorisation taxonomy and trend reports · Root-cause analyses for recurring categories · Evidence of process or system changes traceable to grievance trends | AC52: — | AE52: Grievances are categorised and root-caused, trends are reported to the governance forum, and there is evidence of systemic changes made in response.
A53: SEC-01 | B53: SEC | C53: Security Safeguards | D53: Reasonable security safeguards programme defined and owned | E53: Critical | F53: =IF(E53="Critical",4,IF(E53="High",3,IF(E53="Medium",2,1))) | G53: 1.4 | H53: Yes | I53: in scope | J53: s.8(5), DPDP Act, 2023 | K53: [Rules citation to be verified] | L53: VERIFY_AGAINST_NOTIFIED_RULES | M53: 3 | N53: =IF(OR(H53="No",M53="",UPPER(M53)="NA"),0,1) | O53: =IF(H53="No","Out of scope",IF(UPPER(M53)="NA","Not applicable",IF(M53="","Not assessed",IF(M53>=4,"Compliant",IF(M53>=3,"Substantially compliant",IF(M53>=2,"Partially compliant","Non-compliant")))))) | P53: =IF(N53=0,"",F53*(4-M53)) | Q53: =IF(P53="","",IF(P53>=12,"Critical",IF(P53>=8,"High",IF(P53>=4,"Medium",IF(P53>=1,"Low","None"))))) | R53: =IF(AND(N53=1,M53<3),1,0) | S53: =IF(N53=0,"",M53*G53) | T53: =IF(N53=0,"",4*G53) | U53: A security programme aligned to ISO 27001 is defined, owned by the CISO and certified, with the certificate valid to August 2027. The statement of applicability is scoped to the payments platform and excludes the collections subsidiary and the corporate HRMS, both of which hold personal data. | V53: WP-090 | W53: Arjun Nair, Chief Information Security Officer | Y53: A Data Fiduciary must protect personal data in its possession or under its control, including in respect of any processing undertaken by it or on its behalf by a Data Processor, by taking reasonable security safeguards to prevent a personal data breach. | Z53: Is there a defined, owned and approved set of security safeguards for personal data specifically — mapped to the measures the Rules prescribe — rather than a general IT security posture assumed to be sufficient? | AA53: Inspect the safeguards standard and its mapping to prescribed measures; enquire of the owner; corroborate implementation for a sample of measures. | AB53: Approved security standard applicable to personal data, with named owner · Mapping of implemented controls to each prescribed safeguard · Evidence of periodic review and of gaps being tracked | AC53: Up to INR 250 crore | AD53: 1 | AE53: A personal-data-specific safeguards standard is approved and owned, explicitly mapped to each prescribed measure, with residual gaps tracked and periodically reviewed.
A54: SEC-02 | B54: SEC | C54: Security Safeguards | D54: Access control and least privilege over personal data | E54: Critical | F54: =IF(E54="Critical",4,IF(E54="High",3,IF(E54="Medium",2,1))) | G54: 1.3 | H54: Yes | I54: in scope | J54: s.8(4), s.8(5), DPDP Act, 2023 | K54: [Rules citation to be verified] | L54: VERIFY_AGAINST_NOTIFIED_RULES | M54: 3 | N54: =IF(OR(H54="No",M54="",UPPER(M54)="NA"),0,1) | O54: =IF(H54="No","Out of scope",IF(UPPER(M54)="NA","Not applicable",IF(M54="","Not assessed",IF(M54>=4,"Compliant",IF(M54>=3,"Substantially compliant",IF(M54>=2,"Partially compliant","Non-compliant")))))) | P54: =IF(N54=0,"",F54*(4-M54)) | Q54: =IF(P54="","",IF(P54>=12,"Critical",IF(P54>=8,"High",IF(P54>=4,"Medium",IF(P54>=1,"Low","None"))))) | R54: =IF(AND(N54=1,M54<3),1,0) | S54: =IF(N54=0,"",M54*G54) | T54: =IF(N54=0,"",4*G54) | U54: Role-based access control is enforced through Okta with quarterly recertification for production systems. Recertification does not extend to Snowflake, where 41 analyst accounts hold read access to unmasked customer tables, including 7 belonging to former contractors whose engagements have ended. | V54: WP-091 | W54: Arjun Nair, Chief Information Security Officer | Y54: Reasonable security safeguards include controls that restrict access to personal data to those who require it, as part of appropriate technical and organisational measures. | Z54: Is access to personal data granted on least privilege, subject to periodic recertification, and promptly revoked on role change or exit — including for engineers with production database access and for vendor accounts? | AA54: Inspect access lists against role requirements; test leaver revocation for a sample; re-perform a privilege review for one high-risk system. | AB54: Role-based access model with documented entitlements per role · Periodic access recertification records with evidence of revocations · Leaver and role-change revocation testing, including vendor accounts | AC54: Up to INR 250 crore | AD54: 1 | AE54: Least privilege is enforced with just-in-time or approval-gated access to production personal data, recertification is timely and evidenced with actual revocations, and leaver revocation testing passes.
A55: SEC-03 | B55: SEC | C55: Security Safeguards | D55: Encryption, masking or obfuscation of personal data | E55: Critical | F55: =IF(E55="Critical",4,IF(E55="High",3,IF(E55="Medium",2,1))) | G55: 1.3 | H55: Yes | I55: in scope | J55: s.8(5) read with the Rules, DPDP Act, 2023 | K55: [Rules citation to be verified] | L55: VERIFY_AGAINST_NOTIFIED_RULES | M55: 3 | N55: =IF(OR(H55="No",M55="",UPPER(M55)="NA"),0,1) | O55: =IF(H55="No","Out of scope",IF(UPPER(M55)="NA","Not applicable",IF(M55="","Not assessed",IF(M55>=4,"Compliant",IF(M55>=3,"Substantially compliant",IF(M55>=2,"Partially compliant","Non-compliant")))))) | P55: =IF(N55=0,"",F55*(4-M55)) | Q55: =IF(P55="","",IF(P55>=12,"Critical",IF(P55>=8,"High",IF(P55>=4,"Medium",IF(P55>=1,"Low","None"))))) | R55: =IF(AND(N55=1,M55<3),1,0) | S55: =IF(N55=0,"",M55*G55) | T55: =IF(N55=0,"",4*G55) | U55: Data is encrypted at rest with AWS KMS and in transit with TLS 1.2 or above. Column-level masking is applied in the production database but not in Snowflake or in the pre-production environments, which are refreshed from production without obfuscation. | V55: WP-092 | W55: Arjun Nair, Chief Information Security Officer | Y55: Reasonable security safeguards are understood to include measures such as encryption, obfuscation, masking or the use of virtual tokens to protect personal data. | Z55: Is personal data protected in transit and at rest, and is it masked or tokenised in non-production environments, logs, analytics extracts and support tooling? | AA55: Inspect encryption configuration for transport and storage; test non-production environments and logs for unmasked personal data. | AB55: Transport and at-rest encryption configuration with key management · Masking or tokenisation in non-production, logs and analytics extracts · Evidence of testing for unmasked personal data outside production | AC55: Up to INR 250 crore | AD55: 1 | AE55: Encryption covers transit and rest with managed keys, non-production data is masked or synthetic, logs and analytics extracts are scrubbed, and testing confirms no unmasked personal data outside production.
A56: SEC-04 | B56: SEC | C56: Security Safeguards | D56: Logging, monitoring and detection | E56: High | F56: =IF(E56="Critical",4,IF(E56="High",3,IF(E56="Medium",2,1))) | G56: 1.2 | H56: Yes | I56: in scope | J56: s.8(5) read with the Rules, DPDP Act, 2023 | K56: [Rules citation to be verified] | L56: VERIFY_AGAINST_NOTIFIED_RULES | M56: 4 | N56: =IF(OR(H56="No",M56="",UPPER(M56)="NA"),0,1) | O56: =IF(H56="No","Out of scope",IF(UPPER(M56)="NA","Not applicable",IF(M56="","Not assessed",IF(M56>=4,"Compliant",IF(M56>=3,"Substantially compliant",IF(M56>=2,"Partially compliant","Non-compliant")))))) | P56: =IF(N56=0,"",F56*(4-M56)) | Q56: =IF(P56="","",IF(P56>=12,"Critical",IF(P56>=8,"High",IF(P56>=4,"Medium",IF(P56>=1,"Low","None"))))) | R56: =IF(AND(N56=1,M56<3),1,0) | S56: =IF(N56=0,"",M56*G56) | T56: =IF(N56=0,"",4*G56) | U56: Centralised logging into a managed SIEM covers all in-scope production systems, with documented use cases for privileged access, bulk export and anomalous query patterns. Alert tuning is reviewed monthly and the 24x7 monitoring arrangement was evidenced through three sampled alerts and their disposition. | V56: WP-093 | W56: Arjun Nair, Chief Information Security Officer | Y56: Safeguards to prevent a personal data breach include the ability to detect unauthorised access, and the retention of logs to enable investigation. | Z56: Are access and activity logs over personal data captured, retained for the prescribed period, protected from tampering, and actively monitored with alerting — as opposed to retained but never examined? | AA56: Inspect logging coverage and retention configuration; test alerting by reviewing recent detections and their handling; assess log integrity controls. | AB56: Logging coverage across systems holding personal data, including administrative access · Retention configuration meeting the prescribed period, with tamper protection · Alert definitions and evidence of alerts investigated and closed | AC56: Up to INR 250 crore | AD56: 1 | AE56: Comprehensive tamper-protected logging is retained for the prescribed period, anomalous access generates alerts, and there is evidence of alerts being investigated and closed.
A57: SEC-05 | B57: SEC | C57: Security Safeguards | D57: Vulnerability management and patching | E57: High | F57: =IF(E57="Critical",4,IF(E57="High",3,IF(E57="Medium",2,1))) | G57: 1.2 | H57: Yes | I57: in scope | J57: s.8(5), DPDP Act, 2023 | K57: [Rules citation to be verified] | L57: VERIFY_AGAINST_NOTIFIED_RULES | M57: 3 | N57: =IF(OR(H57="No",M57="",UPPER(M57)="NA"),0,1) | O57: =IF(H57="No","Out of scope",IF(UPPER(M57)="NA","Not applicable",IF(M57="","Not assessed",IF(M57>=4,"Compliant",IF(M57>=3,"Substantially compliant",IF(M57>=2,"Partially compliant","Non-compliant")))))) | P57: =IF(N57=0,"",F57*(4-M57)) | Q57: =IF(P57="","",IF(P57>=12,"Critical",IF(P57>=8,"High",IF(P57>=4,"Medium",IF(P57>=1,"Low","None"))))) | R57: =IF(AND(N57=1,M57<3),1,0) | S57: =IF(N57=0,"",M57*G57) | T57: =IF(N57=0,"",4*G57) | U57: Vulnerability scanning runs weekly with defined remediation SLAs. Of 23 critical findings raised in the period, 19 were closed within SLA; the four exceptions relate to the legacy PPI ledger and have been open for over 120 days without a documented risk acceptance. | V57: WP-094 | W57: Arjun Nair, Chief Information Security Officer | Y57: Taking reasonable safeguards to prevent a breach requires identification and remediation of known vulnerabilities in systems processing personal data. | Z57: Are systems holding personal data scanned and penetration tested on a defined cycle, with findings remediated to timescales tied to severity, and is the remediation backlog aged and reported? | AA57: Inspect scan and test reports; test remediation timeliness against stated timescales; review the aged backlog for overdue critical findings. | AB57: Vulnerability scan and penetration test reports for the current cycle · Remediation timescales by severity and performance against them · Aged backlog with escalation of overdue high-severity items | AC57: Up to INR 250 crore | AD57: 1 | AE57: Scanning and testing run on a defined cycle, remediation meets severity-based timescales, and the aged backlog is reported to governance with overdue items escalated.
A58: SEC-06 | B58: SEC | C58: Security Safeguards | D58: Secure development and change control | E58: High | F58: =IF(E58="Critical",4,IF(E58="High",3,IF(E58="Medium",2,1))) | G58: 1.1 | H58: Yes | I58: in scope | J58: s.8(4), s.8(5), DPDP Act, 2023 | K58: [Rules citation to be verified] | L58: VERIFY_AGAINST_NOTIFIED_RULES | M58: 3 | N58: =IF(OR(H58="No",M58="",UPPER(M58)="NA"),0,1) | O58: =IF(H58="No","Out of scope",IF(UPPER(M58)="NA","Not applicable",IF(M58="","Not assessed",IF(M58>=4,"Compliant",IF(M58>=3,"Substantially compliant",IF(M58>=2,"Partially compliant","Non-compliant")))))) | P58: =IF(N58=0,"",F58*(4-M58)) | Q58: =IF(P58="","",IF(P58>=12,"Critical",IF(P58>=8,"High",IF(P58>=4,"Medium",IF(P58>=1,"Low","None"))))) | R58: =IF(AND(N58=1,M58<3),1,0) | S58: =IF(N58=0,"",M58*G58) | T58: =IF(N58=0,"",4*G58) | U58: Change management is enforced through Freshservice with peer review and automated security testing in the pipeline. Emergency changes bypass the control and 14 per cent of production changes in the period were classified as emergency, which is high enough to weaken the assurance the control provides. | V58: WP-095 | W58: Devika Iyer, VP Engineering | Y58: Appropriate technical and organisational measures extend to the process by which systems processing personal data are built and changed. | Z58: Do changes to systems processing personal data pass through security review, testing and approval, with secrets management and code review enforced rather than advisory? | AA58: Inspect the change control process; sample recent changes to personal-data systems for evidence of review and approval; test secrets handling in the repository. | AB58: Change control procedure with mandatory security review gates · Sample change records showing review and approval before deployment · Secrets management implementation and evidence of repository scanning | AC58: Up to INR 250 crore | AD58: 1 | AE58: Security review is a mandatory gate with evidence of enforcement, code review is required, secrets are centrally managed, and repository scanning confirms no embedded credentials.
A59: SEC-07 | B59: SEC | C59: Security Safeguards | D59: Backup, recovery and integrity | E59: High | F59: =IF(E59="Critical",4,IF(E59="High",3,IF(E59="Medium",2,1))) | G59: 1.1 | H59: Yes | I59: in scope | J59: s.8(4), s.8(5) read with the Rules, DPDP Act, 2023 | K59: [Rules citation to be verified] | L59: VERIFY_AGAINST_NOTIFIED_RULES | M59: 4 | N59: =IF(OR(H59="No",M59="",UPPER(M59)="NA"),0,1) | O59: =IF(H59="No","Out of scope",IF(UPPER(M59)="NA","Not applicable",IF(M59="","Not assessed",IF(M59>=4,"Compliant",IF(M59>=3,"Substantially compliant",IF(M59>=2,"Partially compliant","Non-compliant")))))) | P59: =IF(N59=0,"",F59*(4-M59)) | Q59: =IF(P59="","",IF(P59>=12,"Critical",IF(P59>=8,"High",IF(P59>=4,"Medium",IF(P59>=1,"Low","None"))))) | R59: =IF(AND(N59=1,M59<3),1,0) | S59: =IF(N59=0,"",M59*G59) | T59: =IF(N59=0,"",4*G59) | U59: Backups are encrypted, replicated across availability zones and restore-tested quarterly. The two restore tests in the period met their objectives and are documented with evidence of data integrity verification. | V59: WP-096 | W59: Arjun Nair, Chief Information Security Officer | Y59: Safeguards are understood to include measures for continued processing in the event of loss of availability, including backups, and for maintaining the integrity of personal data. | Z59: Are backups of personal data taken, encrypted, access-controlled and restore-tested — and is the retention and erasure position for backups reconciled with the erasure obligation? | AA59: Inspect backup configuration and encryption; review restore test records; assess how erasure requests are reconciled against backup media. | AB59: Backup configuration with encryption and restricted access · Restore test records with dates and outcomes · Documented position on erasure and backups, including re-erasure on restore | AC59: Up to INR 250 crore | AD59: 1 | AE59: Backups are encrypted and access-controlled, restore testing is periodic and evidenced, and a documented position governs erasure in backups including re-erasure following restore.
A60: SEC-08 | B60: SEC | C60: Security Safeguards | D60: Personnel, endpoint and physical safeguards | E60: High | F60: =IF(E60="Critical",4,IF(E60="High",3,IF(E60="Medium",2,1))) | G60: 1.1 | H60: Yes | I60: in scope | J60: s.8(4), s.8(5), DPDP Act, 2023 | K60: [Rules citation to be verified] | L60: VERIFY_AGAINST_NOTIFIED_RULES | M60: 3 | N60: =IF(OR(H60="No",M60="",UPPER(M60)="NA"),0,1) | O60: =IF(H60="No","Out of scope",IF(UPPER(M60)="NA","Not applicable",IF(M60="","Not assessed",IF(M60>=4,"Compliant",IF(M60>=3,"Substantially compliant",IF(M60>=2,"Partially compliant","Non-compliant")))))) | P60: =IF(N60=0,"",F60*(4-M60)) | Q60: =IF(P60="","",IF(P60>=12,"Critical",IF(P60>=8,"High",IF(P60>=4,"Medium",IF(P60>=1,"Low","None"))))) | R60: =IF(AND(N60=1,M60<3),1,0) | S60: =IF(N60=0,"",M60*G60) | T60: =IF(N60=0,"",4*G60) | U60: Background verification, confidentiality undertakings, endpoint management and data loss prevention are in place for employees. Contractors in the collections subsidiary use personally-owned devices with no endpoint control, and physical access to the collections floor is not restricted from the general office area. | V60: WP-097 | W60: Arjun Nair, Chief Information Security Officer | Y60: Organisational safeguards extend to the people and devices through which personal data is accessed, and to physical records where digitised data originates. | Z60: Are personnel with access to personal data subject to background verification and confidentiality obligations, are endpoints managed and encrypted, and is data exfiltration controlled — including via support tooling and bulk export? | AA60: Inspect personnel screening and confidentiality records; test endpoint management coverage; assess controls over bulk export and removable media. | AB60: Background verification and confidentiality undertakings for personnel with access · Endpoint management and encryption coverage reports · Controls over bulk export, removable media and screen capture in support tooling | AC60: Up to INR 250 crore | AD60: 1 | AE60: Screening and confidentiality obligations are complete, endpoint coverage is near-total and evidenced, and bulk export is gated by approval and monitored with alerting.
A61: SEC-09 | B61: SEC | C61: Security Safeguards | D61: Effectiveness of safeguards independently tested | E61: High | F61: =IF(E61="Critical",4,IF(E61="High",3,IF(E61="Medium",2,1))) | G61: 1.2 | H61: Yes | I61: in scope | J61: s.8(5), DPDP Act, 2023 | K61: [Rules citation to be verified] | L61: VERIFY_AGAINST_NOTIFIED_RULES | M61: 3 | N61: =IF(OR(H61="No",M61="",UPPER(M61)="NA"),0,1) | O61: =IF(H61="No","Out of scope",IF(UPPER(M61)="NA","Not applicable",IF(M61="","Not assessed",IF(M61>=4,"Compliant",IF(M61>=3,"Substantially compliant",IF(M61>=2,"Partially compliant","Non-compliant")))))) | P61: =IF(N61=0,"",F61*(4-M61)) | Q61: =IF(P61="","",IF(P61>=12,"Critical",IF(P61>=8,"High",IF(P61>=4,"Medium",IF(P61>=1,"Low","None"))))) | R61: =IF(AND(N61=1,M61<3),1,0) | S61: =IF(N61=0,"",M61*G61) | T61: =IF(N61=0,"",4*G61) | U61: Annual penetration testing by an external firm covers the application and infrastructure, and the most recent report is dated March 2026 with findings tracked to closure. Testing has never been directed at the privacy controls themselves — consent enforcement, erasure completeness or access segregation in the warehouse. | V61: WP-098 | W61: Arjun Nair, Chief Information Security Officer | Y61: The standard in section 8(5) is reasonableness, which is assessed against outcomes rather than intent. An entity relying on untested controls cannot demonstrate that its safeguards are reasonable. | Z61: Has the effectiveness of the safeguards been independently tested — internal audit, external assessment, red team — and were the findings remediated and retested? | AA61: Inspect independent assessment reports and management responses; test whether findings were remediated and validated by retest. | AB61: Independent assessment or audit reports covering personal data safeguards · Management responses with owners and dates · Retest evidence confirming remediation | AC61: Up to INR 250 crore | AD61: 1 | AE61: Independent testing occurs on a defined cycle, findings are tracked to closure with owners and dates, and remediation is validated by retest.
A62: BRC-01 | B62: BRC | C62: Personal Data Breach Notification | D62: Personal data breach correctly defined in internal procedure | E62: Critical | F62: =IF(E62="Critical",4,IF(E62="High",3,IF(E62="Medium",2,1))) | G62: 1.3 | H62: Yes | I62: in scope | J62: s.2, DPDP Act, 2023 (definition of "personal data breach"), read with s.8(6) | K62: — | L62: — | M62: 3 | N62: =IF(OR(H62="No",M62="",UPPER(M62)="NA"),0,1) | O62: =IF(H62="No","Out of scope",IF(UPPER(M62)="NA","Not applicable",IF(M62="","Not assessed",IF(M62>=4,"Compliant",IF(M62>=3,"Substantially compliant",IF(M62>=2,"Partially compliant","Non-compliant")))))) | P62: =IF(N62=0,"",F62*(4-M62)) | Q62: =IF(P62="","",IF(P62>=12,"Critical",IF(P62>=8,"High",IF(P62>=4,"Medium",IF(P62>=1,"Low","None"))))) | R62: =IF(AND(N62=1,M62<3),1,0) | S62: =IF(N62=0,"",M62*G62) | T62: =IF(N62=0,"",4*G62) | U62: The incident response procedure defines a personal data breach and correctly captures unauthorised disclosure, acquisition, sharing, use, alteration, destruction and loss of access. The definition is annexed to the security procedure rather than integrated into triage, and the severity matrix used by the on-call team is framed around availability and financial impact only, so a confidentiality-only event scores low and may not escalate. | V62: WP-100 | W62: Arjun Nair, Chief Information Security Officer | Y62: A personal data breach means any unauthorised processing of personal data or accidental disclosure, acquisition, sharing, use, alteration, destruction or loss of access to personal data that compromises its confidentiality, integrity or availability. | Z62: Does the internal definition match the statutory one — capturing loss of availability and integrity, accidental internal disclosure, and unauthorised internal access, not merely external attack? | AA62: Inspect the incident procedure definition against the statutory wording; test classification of a sample of past incidents against it. | AB62: Incident procedure reproducing the statutory definition · Classification criteria distinguishing a personal data breach from other incidents · Sample of past incidents classified against the definition | AC62: Up to INR 200 crore | AD62: 2 | AE62: The definition mirrors the statutory scope, classification criteria are documented and applied consistently, and testing of past incidents confirms correct classification.
A63: BRC-02 | B63: BRC | C63: Personal Data Breach Notification | D63: Detection and escalation capability | E63: Critical | F63: =IF(E63="Critical",4,IF(E63="High",3,IF(E63="Medium",2,1))) | G63: 1.3 | H63: Yes | I63: in scope | J63: s.8(5), s.8(6), DPDP Act, 2023 | K63: [Rules citation to be verified] | L63: VERIFY_AGAINST_NOTIFIED_RULES | M63: 3 | N63: =IF(OR(H63="No",M63="",UPPER(M63)="NA"),0,1) | O63: =IF(H63="No","Out of scope",IF(UPPER(M63)="NA","Not applicable",IF(M63="","Not assessed",IF(M63>=4,"Compliant",IF(M63>=3,"Substantially compliant",IF(M63>=2,"Partially compliant","Non-compliant")))))) | P63: =IF(N63=0,"",F63*(4-M63)) | Q63: =IF(P63="","",IF(P63>=12,"Critical",IF(P63>=8,"High",IF(P63>=4,"Medium",IF(P63>=1,"Low","None"))))) | R63: =IF(AND(N63=1,M63<3),1,0) | S63: =IF(N63=0,"",M63*G63) | T63: =IF(N63=0,"",4*G63) | U63: Detection is strong for infrastructure and application events. Detection of breaches arising from misuse of legitimate access — the Snowflake exposure at SEC-02 being the clearest example — is not covered by any use case, and the two incidents in the period were both identified through customer complaint rather than monitoring. | V63: WP-101 | W63: Arjun Nair, Chief Information Security Officer | Y63: The obligation to intimate a breach presupposes the capability to become aware of it. Detection and internal escalation must be sufficient to bring a breach to the attention of those responsible for notification within the prescribed window. | Z63: How would the entity learn of a breach, and how quickly would it reach the person accountable for notification — including breaches originating at a processor or reported by a customer or researcher? | AA63: Inspect detection sources and escalation paths; measure escalation time in recent incidents; test the intake route for externally reported breaches. | AB63: Detection sources including monitoring, processor notification and external reports · Escalation path with defined timescales to the accountable owner · Measured escalation times from recent incidents | AC63: Up to INR 200 crore | AD63: 2 | AE63: Multiple detection sources feed a defined escalation path with timescales that fit inside the notification window, externally reported breaches have a published intake route, and escalation times are measured.
A64: BRC-03 | B64: BRC | C64: Personal Data Breach Notification | D64: Intimation to the Board in the prescribed form and time | E64: Critical | F64: =IF(E64="Critical",4,IF(E64="High",3,IF(E64="Medium",2,1))) | G64: 1.4 | H64: Yes | I64: in scope | J64: s.8(6), DPDP Act, 2023 | K64: [Rules citation to be verified] | L64: VERIFY_AGAINST_NOTIFIED_RULES | M64: 2 | N64: =IF(OR(H64="No",M64="",UPPER(M64)="NA"),0,1) | O64: =IF(H64="No","Out of scope",IF(UPPER(M64)="NA","Not applicable",IF(M64="","Not assessed",IF(M64>=4,"Compliant",IF(M64>=3,"Substantially compliant",IF(M64>=2,"Partially compliant","Non-compliant")))))) | P64: =IF(N64=0,"",F64*(4-M64)) | Q64: =IF(P64="","",IF(P64>=12,"Critical",IF(P64>=8,"High",IF(P64>=4,"Medium",IF(P64>=1,"Low","None"))))) | R64: =IF(AND(N64=1,M64<3),1,0) | S64: =IF(N64=0,"",M64*G64) | T64: =IF(N64=0,"",4*G64) | U64: The procedure requires intimation to the Board but names neither the form nor the period, both of which are left as 'per applicable law'. Neither of the two incidents in the period was assessed for reportability, and no intimation has ever been prepared or rehearsed. Given that s.8(6) carries the second highest penalty in the Schedule, the absence of an operable mechanism is a material exposure. | V64: WP-102 | W64: Meera Raghunathan, Head of Legal & Compliance | Y64: In the event of a personal data breach, the Data Fiduciary must give the Board intimation of the breach in such form and manner as may be prescribed. | Z64: Is the prescribed form, content and timing of intimation to the Board built into the incident runbook, with a pre-drafted template and a named signatory available out of hours? | AA64: Inspect the runbook and notification template against the prescribed requirements; test the availability of the signatory and the submission channel. | AB64: Runbook step with the prescribed timescale and content requirements · Pre-drafted intimation template covering every prescribed field · Named signatory with an out-of-hours deputy, and a tested submission route | AC64: Up to INR 200 crore | AD64: 2 | AE64: A pre-drafted template covers every prescribed field, the timescale is embedded with escalation, the signatory has a deputy, and the submission route has been tested.
... A88: SDF-06 | B88: SDF | C88: Significant Data Fiduciary Obligations | D88: Transfer restrictions applicable to a Significant Data Fiduciary | E88: High | F88: =IF(E88="Critical",4,IF(E88="High",3,IF(E88="Medium",2,1))) | G88: 1.1 | H88: Yes | I88: in scope | J88: s.10(2)(c) read with s.16, DPDP Act, 2023 | K88: [Rules citation to be verified] | L88: VERIFY_AGAINST_NOTIFIED_RULES | M88: 2 | N88: =IF(OR(H88="No",M88="",UPPER(M88)="NA"),0,1) | O88: =IF(H88="No","Out of scope",IF(UPPER(M88)="NA","Not applicable",IF(M88="","Not assessed",IF(M88>=4,"Compliant",IF(M88>=3,"Substantially compliant",IF(M88>=2,"Partially compliant","Non-compliant")))))) | P88: =IF(N88=0,"",F88*(4-M88)) | Q88: =IF(P88="","",IF(P88>=12,"Critical",IF(P88>=8,"High",IF(P88>=4,"Medium",IF(P88>=1,"Low","None"))))) | R88: =IF(AND(N88=1,M88<3),1,0) | S88: =IF(N88=0,"",M88*G88) | T88: =IF(N88=0,"",4*G88) | U88: The entity has not identified whether any transfer restriction specific to a Significant Data Fiduciary applies to it, and has no process for monitoring the position. The gap follows from XBD-02 and would be closed by the same mechanism. | V88: WP-145 | W88: Meera Raghunathan, Head of Legal & Compliance | Y88: Additional measures prescribed for a Significant Data Fiduciary may include restrictions on the transfer outside India of specified categories of personal data or of traffic and flow data. | Z88: Has the entity determined whether any category of personal data or traffic data it holds is subject to a transfer restriction applicable to Significant Data Fiduciaries, and can it evidence compliance? | AA88: Inspect the determination and supporting analysis; reconcile against the transfer map at XBD-01. | AB88: Analysis of applicable transfer restrictions and the categories affected · Reconciliation against the cross-border transfer map · Technical controls preventing restricted transfers | AC88: Up to INR 150 crore | AD88: 4 | AE88: Affected categories are identified, reconciled against the transfer map, and technical controls prevent restricted transfers with monitoring for exceptions.
A89: BRD-01 | B89: BRD | C89: Enforcement Readiness & Board Engagement | D89: Capability to respond to a Board inquiry | E89: Medium | F89: =IF(E89="Critical",4,IF(E89="High",3,IF(E89="Medium",2,1))) | G89: 1 | H89: Yes | I89: in scope | J89: s.27, s.28, s.36, DPDP Act, 2023 | K89: [Rules citation to be verified] | L89: VERIFY_AGAINST_NOTIFIED_RULES | M89: 2 | N89: =IF(OR(H89="No",M89="",UPPER(M89)="NA"),0,1) | O89: =IF(H89="No","Out of scope",IF(UPPER(M89)="NA","Not applicable",IF(M89="","Not assessed",IF(M89>=4,"Compliant",IF(M89>=3,"Substantially compliant",IF(M89>=2,"Partially compliant","Non-compliant")))))) | P89: =IF(N89=0,"",F89*(4-M89)) | Q89: =IF(P89="","",IF(P89>=12,"Critical",IF(P89>=8,"High",IF(P89>=4,"Medium",IF(P89>=1,"Low","None"))))) | R89: =IF(AND(N89=1,M89<3),1,0) | S89: =IF(N89=0,"",M89*G89) | T89: =IF(N89=0,"",4*G89) | U89: The entity has experience of responding to RBI inspections and has a regulatory response process, which provides a partial foundation. No owner is designated for Data Protection Board correspondence, and the evidence deficiencies at GOV-07 and CON-07 mean the entity could not currently produce the consent and notice records an inquiry would be most likely to seek. | V89: WP-150 | W89: Meera Raghunathan, Head of Legal & Compliance | Y89: The Board may, on receipt of a complaint or on reference, inquire into a breach and may require the production of information. An entity must be able to respond within the timescales the Board sets. | Z89: Is there a defined procedure for receiving and responding to a communication from the Board, with a named owner, legal involvement and the ability to assemble evidence at short notice? | AA89: Inspect the procedure and named owner; test evidence assembly by requiring production of a defined evidence set within a short deadline. | AB89: Documented procedure for handling Board communications with a named owner · Evidence repository enabling rapid assembly of compliance artefacts · Legal and communications escalation arrangements | AC89: — | AE89: A defined procedure with a named owner is supported by an organised evidence repository, and testing confirms a complete evidence set can be assembled at short notice.
A90: BRD-02 | B90: BRD | C90: Enforcement Readiness & Board Engagement | D90: Awareness of voluntary undertaking and mitigation as penalty factors | E90: Low | F90: =IF(E90="Critical",4,IF(E90="High",3,IF(E90="Medium",2,1))) | G90: 0.8 | H90: Yes | I90: in scope | J90: s.32, s.33(2), DPDP Act, 2023 | K90: — | L90: — | M90: 1 | N90: =IF(OR(H90="No",M90="",UPPER(M90)="NA"),0,1) | O90: =IF(H90="No","Out of scope",IF(UPPER(M90)="NA","Not applicable",IF(M90="","Not assessed",IF(M90>=4,"Compliant",IF(M90>=3,"Substantially compliant",IF(M90>=2,"Partially compliant","Non-compliant")))))) | P90: =IF(N90=0,"",F90*(4-M90)) | Q90: =IF(P90="","",IF(P90>=12,"Critical",IF(P90>=8,"High",IF(P90>=4,"Medium",IF(P90>=1,"Low","None"))))) | R90: =IF(AND(N90=1,M90<3),1,0) | S90: =IF(N90=0,"",M90*G90) | T90: =IF(N90=0,"",4*G90) | U90: Management was not aware of the voluntary undertaking mechanism or that mitigating action and its timeliness are express factors in determining a penalty. The practical significance — that documented prompt remediation of the findings in this report is itself risk mitigation — had not been considered. | V90: WP-151 | W90: Meera Raghunathan, Head of Legal & Compliance | Y90: The Board may accept a voluntary undertaking at any stage after receipt of a complaint, and in determining the quantum of a penalty must have regard to factors including the promptness, effectiveness and timeliness of mitigating action taken. | Z90: Do those who would manage an enforcement matter understand the voluntary undertaking mechanism and the section 33(2) mitigation factors, so that decisions in the first days of an incident are taken with exposure in mind? | AA90: Enquire of legal and privacy leadership; inspect any playbook addressing enforcement strategy and mitigation documentation. | AB90: Playbook or briefing covering voluntary undertakings and mitigation factors · Practice of contemporaneously documenting mitigating action during incidents · Evidence of legal involvement from the outset of incidents | AC90: — | AE90: Enforcement strategy is documented and understood, mitigating action is recorded contemporaneously during incidents, and legal is engaged from the outset.
A91: BRD-03 | B91: BRD | C91: Enforcement Readiness & Board Engagement | D91: Remediation plan owned, funded and tracked | E91: High | F91: =IF(E91="Critical",4,IF(E91="High",3,IF(E91="Medium",2,1))) | G91: 1.1 | H91: Yes | I91: in scope | J91: s.8(1), s.33(2), DPDP Act, 2023 | K91: — | L91: — | M91: 2 | N91: =IF(OR(H91="No",M91="",UPPER(M91)="NA"),0,1) | O91: =IF(H91="No","Out of scope",IF(UPPER(M91)="NA","Not applicable",IF(M91="","Not assessed",IF(M91>=4,"Compliant",IF(M91>=3,"Substantially compliant",IF(M91>=2,"Partially compliant","Non-compliant")))))) | P91: =IF(N91=0,"",F91*(4-M91)) | Q91: =IF(P91="","",IF(P91>=12,"Critical",IF(P91>=8,"High",IF(P91>=4,"Medium",IF(P91>=1,"Low","None"))))) | R91: =IF(AND(N91=1,M91<3),1,0) | S91: =IF(N91=0,"",M91*G91) | T91: =IF(N91=0,"",4*G91) | U91: A remediation tracker exists and carries 23 open privacy items. Fourteen have no owner, 19 have no target date, and no budget has been allocated for the engineering work that the erasure, consent and withdrawal findings in this report will require. Without funding and ownership the plan is a list rather than a commitment. | V91: WP-152 | W91: Vikram Shetty, Chief Financial Officer | Y91: Accountability under section 8(1), together with the treatment of mitigation as a factor in penalty determination, requires that known gaps be subject to a plan that is actually resourced and progressed. | Z91: Are identified compliance gaps captured in a single plan with named owners, dates and funding, and is progress reported and enforced — or does the plan exist as a document that no one is measured against? | AA91: Inspect the remediation plan and progress reporting; test a sample of items for evidence of actual progress against the recorded dates. | AB91: Consolidated remediation plan with owners, dates, funding and status · Progress reporting to the governance forum · Evidence of items completed and of overdue items escalated | AC91: — | AE91: A funded plan with named owners and dates is reported to governance, completions are evidenced, and overdue items are escalated and replanned deliberately.

Sheet Evidence Log
A1: Workpaper ref | B1: Control ID(s) | C1: Evidence obtained | D1: Type | E1: Source / provided by | F1: Date obtained | G1: Tested by | H1: Conclusion | I1: File location
A2: WP-001 | B2: CON-07 | C2: Export of consent artefacts for 3 sampled Data Principals, showing purpose set, timestamp, interface and notice version | D2: System export | E2: Head of Engineering | F2: 2026-08-14 | G2: (auditor) | H2: Artefacts retrieved for all 3; notice version present. No exception. | I2: /audit/wp/001-consent-export.csv
A3: ↑ example row — overwrite or delete. Rows below are for your entries.

Sheet Citations
B2: Citation Register
B3: The Digital Personal Data Protection Act, 2023 (Act No. 22 of 2023)
B5: PENALTY SCHEDULE — s.33 read with the Schedule
B6: Entry | C6: Breach | D6: Provision | E6: Maximum
B7: Entry 1 | C7: Breach of the obligation to take reasonable security safeguards to prevent personal data breach | D7: s.8(5) | E7: Up to INR 250 crore
B8: Entry 2 | C8: Breach of the obligation to give the Board or affected Data Principal notice of a personal data breach | D8: s.8(6) | E8: Up to INR 200 crore
B9: Entry 3 | C9: Breach of additional obligations in relation to children | D9: s.9 | E9: Up to INR 200 crore
B10: Entry 4 | C10: Breach of additional obligations of a Significant Data Fiduciary | D10: s.10 | E10: Up to INR 150 crore
B11: Entry 5 | C11: Breach of the duties of a Data Principal | D11: s.15 | E11: Up to INR 10,000
B12: Entry 6 | C12: Breach of any term of a voluntary undertaking accepted by the Board | D12: s.32 | E12: Up to the extent applicable for the breach in respect of which proceedings were instituted
B13: Entry 7 | C13: Breach of any other provision of the Act or rules made thereunder (residuary) | D13: residuary | E13: Up to INR 50 crore
B16: DPDP RULES — SLOTS AWAITING VERIFICATION
B17: Populate the citation for each slot in controls/citations.yaml and set its status to VERIFIED_RULES. Every deliverable then updates from that single edit. Until then these citations are deliberately blank rather than reconstructed.
B20: Slot key | C20: Subject matter the Rules address | D20: Act anchor | E20: Controls relying on it
B21: NOTICE_CONTENT | C21: Prescribed form, contents and presentation of the notice given to a Data Principal, including itemised description of personal data and purpose, and clarity/plain-language requirements | D21: s.5(1), s.5(3), s.40(2) | E21: NOT-01, NOT-02, NOT-03, NOT-04, NOT-05
B22: CONSENT_REQUEST_FORM | C22: Manner in which a consent request is to be presented, including plain-language requirement and contact details of the person answering on behalf of the Data Fiduciary | D22: s.6(3) | E22: CON-01, CON-03
B23: CONSENT_MANAGER_REGISTRATION | C23: Conditions of registration of a Consent Manager with the Board, including any minimum net-worth or financial-capacity threshold, technical and operational capability, and governance conditions | D23: s.6(9) | E23: CMG-01
B24: CONSENT_MANAGER_OBLIGATIONS | C24: Obligations of a registered Consent Manager, including consent record-keeping, interoperability, and accountability to the Data Principal | D24: s.6(7), s.6(8), s.6(9) | E24: CMG-02, CMG-03
B25: SECURITY_SAFEGUARDS | C25: Prescribed reasonable security safeguards — understood to address measures such as encryption/obfuscation/masking, access control, monitoring and logging, retention of logs, backup and recovery, and contractual flow-down to processors | D25: s.8(4), s.8(5) | E25: PRO-03, SEC-01, SEC-02, SEC-03, SEC-04, SEC-05, SEC-06, SEC-07, SEC-08, SEC-09
B26: BREACH_INTIMATION | C26: Form, contents, timing and manner of intimating a personal data breach to the Board and to each affected Data Principal, including any initial-versus-detailed reporting split and the outer time limit | D26: s.8(6) | E26: BRC-02, BRC-03, BRC-04
B27: RETENTION_ERASURE_PERIODS | C27: Time periods after which personal data must be erased, and the classes of Data Fiduciary and user-count thresholds to which specified periods apply; also any pre-erasure advance notice to the Data Principal | D27: s.8(7), s.8(10) | E27: RET-01, RET-02, RET-03, RET-04, RET-05
B28: DP_CONTACT_PUBLICATION | C28: Manner of publishing the business contact information of the Data Protection Officer, or of the person able to answer questions about processing on behalf of the Data Fiduciary | D28: s.8(8) | E28: GOV-03
B29: GRIEVANCE_RESPONSE_PERIOD | C29: Period within which a Data Fiduciary or Consent Manager must respond to a grievance of a Data Principal | D29: s.13(2) | E29: GRV-02
B30: RIGHTS_REQUEST_HANDLING | C30: Manner in which a Data Principal makes a request to exercise rights, and the manner and period for the Data Fiduciary's response, including verification of identity | D30: s.11, s.12, s.13 | E30: RGT-01, RGT-02, RGT-03, RGT-05, RGT-06
B31: NOMINATION | C31: Manner in which a Data Principal may nominate another individual to exercise rights in the event of death or incapacity | D31: s.14 | E31: RGT-04
... B41: COMMENCEMENT_PHASING | C41: Dates on which particular provisions of the Act and Rules come into force, including any phased or tranched commencement schedule | D41: s.1(2) | E41: APP-05
